Workbook

Sheet ALL_TEXT
A1: Participant Number | B1: Track ID | C1: Full Text | D1: Positive | E1: Favourite | F1: Negative | G1: Familiar | H1: Unfamiliar | I1: Musical Expressive Characteristics | J1: Lyrics | K1: Musical Meaning | L1: Bass Line | M1: Beat | N1: Hook | O1: Instrumentation | P1: Melody | Q1: Performer | R1: Production | S1: Rhythm | T1: Riffs-Ornamentation | U1: Song Structure/Composition | V1: Sound | W1: Style | X1: Tempo | Y1: Vocals | Z1: Album | AA1: Artist | AB1: Era | AC1: Genre | AD1: Version | AE1: Other Forms of Media | AF1: Film | AG1: Music Video | AH1: Musical | AI1: Playlist | AJ1: Television | AK1: Memory | AL1: Discovery | AM1: Emotion | AN1: Event/Concert | AO1: Personal Event | AP1: Vacation | AQ1: Place | AR1: Time or Stage in Life | AS1: Girft/Recommendation | AT1: Rediscovery | AU1: Reminisce- Nostalgia | AV1: Personal Performance | AW1: People | AX1: Being Alone | AY1: Family | AZ1: Friends | BA1: Loss of a person | BB1: Romantic relationship | BC1: Recommendation from Friend/Family | BD1: Accompaniment | BE1: Dancing | BF1: Driving | BG1: Exercising | BH1: Partying | BI1: Singing | BJ1: Sleeping | BK1: Walking | BL1: Working | BM1: Imagination | BN1: Season/time of day/weather | BO1: Christmas | BP1: Summer | BQ1: Create Atmosphere | BR1: Change Mood | BS1: Stress/Frustration/Tension | BT1: Calm | BU1: Energy | BV1: Happiness-good mood | BW1: Motivation/focus | BX1: Sadness | BY1: Match Mood | BZ1: No relationship | CA1: Participating in the study
A2: 1 | B2: a | C2: My teenage years I downloaded the whole album as I like the band It reminds me of the period in my life where I'd listen to Green Day frequently In the respect that it reminds me of a time of my life, yes | D2: My teenage years I downloaded the whole album as I like the band | Z2: My teenage years I downloaded the whole album as I like the band | AA2: My teenage years I downloaded the whole album as I like the band/ It reminds me of the period in my life where I'd listen to Green Day frequentl | AR2: My teenage years I downloaded the whole album as I like the band/It reminds me of the period in my life where I'd listen to Green Day frequentl/ In the respect that it reminds me of a time of my life, yes
A3: 1 | B3: b | C3: I don't actually know or remember it I believe I got it when I downloaded a single I don't know the track No - as above | H3: I don't actually know or remember it / I don't know the track | BZ3: No - as above
A4: 2 | B4: a | C4: Emotion I like the song and I really like the singers voice I like the groove of the chorus, I like his voice as it can be warm and melodic but also raspy and I like the style of the music, it's pop-rock No, but I have good memories of seeing the band live. I dont have a personal connection to the lyrics. | D4: I like the song and I really like the singers voice | J4: I dont have a personal connection to the lyrics. | U4: I like the groove of the chorus | W4: I like the groove of the chorus / I like his voice as it can be warm and melodic but also raspy and I like the style of the music, it's pop-rock | Y4: I like the song and I really like the singers voice / I like his voice as it can be warm and melodic but also raspy and I like the style of the music, it's pop-rock | AA4: No, but I have good memories of seeing the band live. | AC4: I like his voice as it can be warm and melodic but also raspy and I like the style of the music, it's pop-rock | AM4: Emotion | AN4: No, but I have good memories of seeing the band live. | BZ4: No, but I have good memories of seeing the band live. / I dont have a personal connection to the lyrics.
A5: 2 | B5: b | C5: I saw Beth sing this live and she said the title comes from a quote by Leonard Cohen, when he said he wasn't a "love gangster", Beth decided this was a great title for a song It's from her new album, and I am a big fan of her songs It has a bluesy feel to it. I really like Beth Harts voice Well since leonard cohen died recently I think of this song as a sort of tribute to him. I am always emotionally invested in Beth Harts songs because she is a very honest and open songwriter and singer | D5: I saw Beth sing this live and she said the title comes from a quote by Leonard Cohen, when he said he wasn't a "love gangster", Beth decided this was a great title for a song It's from her new album, and I am a big fan of her songs/ I really like Beth Harts voice | K5: Well since leonard cohen died recently I think of this song as a sort of tribute to him/ I am always emotionally invested in Beth Harts songs because she is a very honest and open songwriter and singer | Q5: am always emotionally invested in Beth Harts songs because she is a very honest and open songwriter and singer, . I really like Beth Harts voice | Y5: I really like Beth Harts voice | Z5: I saw Beth sing this live and she said the title comes from a quote by Leonard Cohen, when he said he wasn't a "love gangster", Beth decided this was a great title for a song It's from her new album, and I am a big fan of her songs | AA5: I saw Beth sing this live and she said the title comes from a quote by Leonard Cohen, when he said he wasn't a "love gangster", Beth decided this was a great title for a song It's from her new album, and I am a big fan of her songs/ I am always emotionally invested in Beth Harts songs because she is a very honest and open songwriter and singer | AC5: It has a bluesy feel to it. | AN5: I saw Beth sing this live and she said the title comes from a quote by Leonard Cohen, when he said he wasn't a "love gangster", Beth decided this was a great title for a song It's from her new album, and I am a big fan of her songs
A6: 3 | B6: a | C6: The story told in the lyrics. The lyrics are engaging & i wanted to be able to easily find the track. Its a relaxing beat with a complicated message which makes the song engaging. no | I6: Its a relaxing beat, with a complicated message which makes the song engaging | J6: The story told in the lyrics. / The lyrics are engaging & i wanted to be able to easily find the track. | K6: The story told in the lyrics. / Its a relaxing beat with a complicated message which makes the song engaging. | M6: Its a relaxing beat with a complicated message which makes the song engaging. | BS6: Its a relaxing beat with a complicated message which makes the song engaging. | BT6: Its a relaxing beat with a complicated message which makes the song engaging. | BZ6: no
A7: 3 | B7: b | C7: Kendrick Lemar's verse It's a very good song. The various verses/ artists all in one track. No | D7: It's a very good song. | U7: Kendrick Lemar's verse / The various verses/ artists all in one track. | AA7: Kendrick Lemar's verse / The various verses/ artists all in one track. | BZ7: No
A8: 4 | B8: a | C8: Peaceful Gorgeous song, rich voice, really simple composition Always calms me down; reminds me to look for what's beautiful Yes -- although I'd maybe say "connection" instead of relationship; inspires an emotional response & have listened to it on repeat before | D8: Peaceful Gorgeous song, rich voice, really simple composition | G8: Yes -- although I'd maybe say "connection" instead of relationship; inspires an emotional response & have listened to it on repeat before | I8: Peaceful Gorgeous song, rich voice, really simple composition | U8: Peaceful Gorgeous song, rich voice, really simple composition | Y8: Peaceful Gorgeous song, rich voice, really simple composition | AM8: inspires an emotional response & have listened to it on repeat before | BR8: Always calms me down; reminds me to look for what's beautiful / inspires an emotional response & have listened to it on repeat before | BS8: Always calms me down; reminds me to look for what's beautiful | BT8: Peaceful Gorgeous song, rich voice, really simple composition Gorgeous song, rich voice, really simple composition / Always calms me down; reminds me to look for what's beautiful
A9: 4 | B9: b
A10: 5 | B10: a | C10: Last summer 2016 I liked the song very much when I heard it for the first time. It makes me happy. It has nice melody and the cumbia rhythm makes me feel happy. I want to sing along and dance at the same time. Yes. This band is one of my favorites and this song brings happy summer feeling to me. | D10: I liked the song very much when I heard it for the first time. | E10: This band is one of my favorites and this song brings happy summer feeling to me. | G10: Yes | P10: It has nice melody and the cumbia rhythm makes me feel happy. | S10: It has nice melody and the cumbia rhythm makes me feel happy. | AA10: This band is one of my favorites and this song brings happy summer feeling to me. | AL10: I liked the song very much when I heard it for the first time. | AR10: Last summer 2016 | BE10: I want to sing along and dance at the same time. | BI10: I want to sing along and dance at the same time | BP10: Last summer 2016 / This band is one of my favorites and this song brings happy summer feeling to me. | BR10: This band is one of my favorites and this song brings happy summer feeling to me. | BV10: It makes me happy / It has nice melody and the cumbia rhythm makes me feel happy. / This band is one of my favorites and this song brings happy summer feeling to me.
A11: 5 | B11: b | C11: Summer and sunny days I like it a lot. It makes me happy. Not really. | D11: I like it a lot. | BN11: Summer and sunny days I like it a lot | BP11: Summer and sunny days | BV11: . It makes me happy. | BZ11: Not really.
A12: 6 | B12: a | C12: Hit-Girl's hallway attack The Kick-ass soundtrack Great up beat tempo and fond memories Yes, it's in a great scene from my favorite movie | D12: Great up beat tempo and fond memories/ Yes, it's in a great scene from my favorite movie | E12: Yes, it's in a great scene from my favorite movie | G12: Yes, it's in a great scene from my favorite movie | I12: The Kick-ass soundtrack,Great up beat tempo | M12: Great up beat tempo and fond memories | X12: Great up beat tempo and fond memories | AF12: Hit-Girl's hallway attack / The Kick-ass soundtrack / Yes, it's in a great scene from my favorite movie
A13: 6 | B13: b
A14: 7 | B14: a | C14: It makes me think about walking to work on a cool summer night. Because it's a great song that makes me feel positive emotions The way it makes me feel, the uniqueness of the singers voice, the cadence of the music Yes, it brings back fond memories of my home-town. Particularly first meeting me boyfriend. | D14: Because it's a great song that makes me feel positive emotions | G14: Yes, it brings back fond memories of my home-town | U14: The way it makes me feel, the uniqueness of the singers voice, the cadence of the music | Y14: The way it makes me feel, the uniqueness of the singers voice, the cadence of the music | AM14: The way it makes me feel, the uniqueness of the singers voice, the cadence of the music | AQ14: Yes, it brings back fond memories of my home-town | BB14: Particularly first meeting me boyfriend. | BK14: It makes me think about walking to work on a cool summer night | BN14: It makes me think about walking to work on a cool summer night | BP14: It makes me think about walking to work on a cool summer night | BR14: Because it's a great song that makes me feel positive emotions / The way it makes me feel, the uniqueness of the singers voice, the cadence of the music | BV14: Because it's a great song that makes me feel positive emotions
A15: 7 | B15: b | C15: It makes me feel sad because of the recent passing of the genius that is Bowie. Because Bowie is my favourite artist It is a classic Yes, this song makes me feel filled with energy and optimism. | E15: Because Bowie is my favourite artist | G15: Yes, this song makes me feel filled with energy and optimism. | I15: Because Bowie is my favourite artist It is a classic | AA15: It makes me feel sad because of the recent passing of the genius that is Bowie/ Because Bowie is my favourite artist | BA15: It makes me feel sad because of the recent passing of the genius that is Bowie | BU15: Yes, this song makes me feel filled with energy and optimism. | BV15: Yes, this song makes me feel filled with energy and optimism. | BX15: It makes me feel sad because of the recent passing of the genius that is Bowie
A16: 8 | B16: a | C16: I remember positive worship experiences listening to this track, both on my phone and live at Church. I have a playlist of worship music I listen to regularly. I feel uplifted, by the music and also by the spiritual connection I feel when I worship. Yes, in the sense that I don't just passively listen but engage in an act of worship through listening or singing along with a heart open to my God. | G16: Yes, in the sense that I don't just passively listen but engage in an act of worship through listening or singing along with a heart open to my God. / Yes - reguarly listen to it since it's been released/ large mutual enjoyment with friends | K16: I feel uplifted, by the music and also by the spiritual connection I feel when I worship | AI16: I have a playlist of worship music I listen to regularly. | AO16: I remember positive worship experiences listening to this track, both on my phone and live at Church | AQ16: I remember positive worship experiences listening to this track, both on my phone and live at Church | AY16: Yes - reguarly listen to it since it's been released/ large mutual enjoyment with friends | BI16: Yes, in the sense that I don't just passively listen but engage in an act of worship through listening or singing along with a heart open to my God. | BQ16: Yes, in the sense that I don't just passively listen but engage in an act of worship through listening or singing along with a heart open to my God. | BR16: I feel uplifted, by the music and also by the spiritual connection I feel when I worship | BV16: I feel uplifted, by the music and also by the spiritual connection I feel when I worship
A17: 8 | B17: b | C17: I don't recognise this, but it's peaceful. I remember looking for some music to support mindfulness meditation a while ago, and must have downloaded it then. I find it peaceful, I instinctively start to focus on my breathing and centre myself when I hear it. No, it isn't one I recall having actively listened to before. | H17: I don't recognise this, but it's peaceful/ No, it isn't one I recall having actively listened to before. | I17: find it peaceful, I instinctively start to focus on my breathing and centre myself when I hear it. | AL17: I remember looking for some music to support mindfulness meditation a while ago, and must have downloaded it then. | BT17: I don't recognise this, but it's peaceful/ I find it peaceful, I instinctively start to focus on my breathing and centre myself when I hear it. | BZ17: No, it isn't one I recall having actively listened to before.
A18: 9 | B18: a | C18: Grime/stank face It's an absolute banger Sickest baseline Yes - reguarly listen to it since it's been released/ large mutual enjoyment with friends | D18: It's an absolute banger/ Sickest baseline / Yes - reguarly listen to it since it's been released/ large mutual enjoyment with friends | G18: reguarly listen to it since it's been released | I18: Grime/stank face, Sickest baseline | L18: Sickest baseline | AC18: Grime/stank face | AZ18: Yes - reguarly listen to it since it's been released/ large mutual enjoyment with friends
A19: 9 | B19: b
A20: 10 | B20: a | C20: Don't know this too well but love the artist New songs by an artist i already love its a good song no; its very new however i feel comfort from that artists voice | D20: Don't know this too well but love the artist/ New songs by an artist i already love/ its a good song | H20: Don't know this too well but love the artist/ no; its very new however i feel comfort from that artists voice | Q20: no; its very new however i feel comfort from that artists voice | Y20: no; its very new however i feel comfort from that artists voice | AA20: Don't know this too well but love the artist/ New songs by an artist i already love/ no; its very new however i feel comfort from that artists voice | BR20: ..in their feeling of comfort. no; its very new however i feel comfort from that artists voice | BT20: no; its very new however i feel comfort from that artists voice | BZ20: no; its very new however i feel comfort from that artists voice
A21: 10 | B21: b | C21: comfort. the film boyhood after hearing it on a films soundtrack i found it and loved it its lyrics are comforting in any mood; it reminds me of the film and of personal feelings yes; it makes me feel confident, independent and also grounded. As someone with anxiety it helps me know i can let go sometimes and not always try and help myself. | D21: i found it and loved it its lyrics are comforting in any mood; it reminds me of the film and of personal feelings | J21: i found it and loved it its lyrics are comforting in any mood; it reminds me of the film and of personal feelings | K21: its lyrics are comforting in any mood; it reminds me of the film and of personal feelings /yes; it makes me feel confident, independent and also grounded. / As someone with anxiety it helps me know i can let go sometimes and not always try and help myself. | AF21: the film boyhood after hearing it on a films soundtrack/ i found it and loved it its lyrics are comforting in any mood; it reminds me of the film and of personal feelings | BS21: As someone with anxiety it helps me know i can let go sometimes and not always try and help myself. | BW21: yes; it makes me feel confident, independent and also grounded. | BY21: i found it and loved it its lyrics are comforting in any mood; it reminds me of the film and of personal feelings
A22: 11 | B22: a | C22: Faith Encourgement It encourages me doing the day No , just started listening to it . | I22: Faith Encourgement | BW22: Faith Encourgement It encourages me doing the day | BZ22: No , just started listening to it .
A23: 11 | B23: b | C23: Joy It gives me hope. I enjoy it because it reminds me not to give up and allows me to express my self Yes, I can play it when encouragement is needed. | I23: Joy | K23: Joy / I enjoy it because it reminds me not to give up and allows me to express my self | BV23: It gives me hope./ I enjoy it because it reminds me not to give up and allows me to express my self | BW23: I enjoy it because it reminds me not to give up and allows me to express my self | BY23: Yes, I can play it when encouragement is needed.
A24: 12 | B24: a | C24: The music video I like the song I like the voices No, it doesn't affect me | D24: I like the song I like the voices | Y24: I like the song I like the voices | AG24: The music video | BZ24: No, it doesn't affect me
A25: 12 | B25: b | C25: The video It's funny It's funny, the lyrics are lewd No | I25: It's funny It's funny, the lyrics are lewd | J25: It's funny It's funny, the lyrics are lewd | AG25: The video | BZ25: No
A26: 13 | B26: a
A27: 13 | B27: b
A28: 14 | B28: a | C28: I want to skip it When I got the track, I loved the song and now I am over it. I am just kinda over it, it is a bit annoying now. Yes, it's my dad's favorite song. | F28: I want to skip it / When I got the track, I loved the song and now I am over it. / I am just kinda over it, it is a bit annoying now. | BS28: I am just kinda over it, it is a bit annoying now. | BZ28: Yes, it's my dad's favorite song.
A29: 14 | B29: b | C29: Spunky I like the song It is so upbeat and so fun. No, its just a good song | D29: I like the song / No, its just a good song | I29: Spunky. It is so upbeat and so fun. | M29: Spunky. It is so upbeat and so fun.
A30: 15 | B30: a | C30: Never heard it before... Wanted to have a Slayer album in my collection. Energetic No | H30: Never heard it before | I30: Energetic | Z30: Wanted to have a Slayer album in my collection. | AA30: Wanted to have a Slayer album in my collection. | AI30: Wanted to have a Slayer album in my collection. | BZ30: No
A31: 15 | B31: b | C31: Moody I like the artist Feels good man. No | D31: I like the artist | I31: Moody | AA31: I like the artist | BQ31: Moody | BR31: Feels good man. | BZ31: No
A32: 16 | B32: a | C32: Relaxed I enjoy listening to relaxed music when doing uni work It relaxes me No | D32: I enjoy listening to relaxed music when doing uni work | BL32: I enjoy listening to relaxed music when doing uni work | BS32: Relaxed/ It relaxes me | BT32: Relaxed/ It relaxes me | BZ32: No
A33: 16 | B33: b | C33: Olympics Liked it a few years ago Memories No | D33: Liked it a few years ago | AK33: Olympics / Memories | BZ33: No
A34: 17 | B34: a | C34: Best concert I've ever been to I want to use it at my wedding The guitar and vocals Yes, Josh Garrels' music meant a lot to me when I was going through a hard time | G34: Yes, Josh Garrels' music meant a lot to me when I was going through a hard time | K34: Josh Garrels' music meant a lot to me when I was going through a hard time | O34: The guitar and vocals | Y34: The guitar and vocals | AA34: Yes, Josh Garrels' music meant a lot to me when I was going through a hard time | AN34: Best concert I've ever been to | AR34: Yes, Josh Garrels' music meant a lot to me when I was going through a hard time | BM34: I want to use it at my wedding
A35: 17 | B35: b | C35: I don't remember this song I saved the whole album I like the band No, I don't remember this song being on the album. As it's playing, I like it more. | D35: I like the band/ As it's playing, I like it more. | H35: I don't remember this song / No, I don't remember this song being on the album. | Z35: I saved the whole album/ , I don't remember this song being on the album | AA35: I like the band
A36: 18 | B36: a | C36: Fun, energised Gets me pumped to do revision It's fun and happy No, I don't feel it on a human level | I36: It's fun and happy, fun, energised | BR36: Fun, energised / Gets me pumped to do revision / It's fun and happy | BU36: Fun, energised | BV36: It's fun and happy | BW36: Gets me pumped to do revision | BZ36: No, I don't feel it on a human level
A37: 18 | B37: b
A38: 19 | B38: a | C38: Its a good song that I've not listened to in a long time! I like Bruno Mars and the song makes me happy! I like Bruno Mars's voice and the dancing beat. No. | D38: Its a good song that I've not listened to in a long time! / I like Bruno Mars and the song makes me happy! / I like Bruno Mars's voice and the dancing beat. | M38: I like Bruno Mars's voice and the dancing beat. | Y38: I like Bruno Mars's voice and the dancing beat. | AA38: I like Bruno Mars and the song makes me happy! / I like Bruno Mars's voice and the dancing beat. | AT38: Its a good song that I've not listened to in a long time! | BV38: I like Bruno Mars and the song makes me happy! | BZ38: No.
A39: 19 | B39: b | C39: Its an old song! its good to dance too :) good to dance to but can get a bit boring and repetitive. no | F39: good to dance to but can get a bit boring and repetitive. | I39: its an old song! good to dance to but can get a bit boring and repetitive. | BE39: its good to dance too :) / good to dance to but can get a bit boring and repetitive. | BZ39: no
A40: 20 | B40: a | C40: Old school hiphop with cool effects Because Run DMC are a classic trio and I like their music. Because its upbeat and makes me feel good, and it's fun to listen to on journeys. Not really, but it reminds me of summer | D40: Because Run DMC are a classic trio and I like their music. | M40: Because its upbeat and makes me feel good, and it's fun to listen to on journeys. | R40: Old school hiphop with cool effects | AA40: Because Run DMC are a classic trio and I like their music. | AC40: Old school hiphop with cool effects | BF40: Because its upbeat and makes me feel good, and it's fun to listen to on journeys. | BP40: Not really, but it reminds me of summer | BR40: Because its upbeat and makes me feel good, and it's fun to listen to on journeys. | BV40: Because its upbeat and makes me feel good, and it's fun to listen to on journeys. | BZ40: Not really, but it reminds me of summer
A41: 20 | B41: b
A42: 21 | B42: a | C42: Enjoyable, want to sing along As part of a album I wanted to listen to Enjoy Yes , evokes memories | D42: Enjoyable, want to sing along/ Enjoy | I42: Enjoyable, Enjoy | Z42: As part of a album I wanted to listen to | AK42: Yes , evokes memories | BI42: Enjoyable, want to sing along
A43: 21 | B43: b | C43: Great song Good track from a great album Good song No | D43: Great song Good track from a great album Good song | Z43: Good track from a great album | BZ43: No
A44: 22 | B44: a | C44: alcohol reminds me of university pre drinks memories no | AR44: reminds me of university pre drinks memories | BH44: alcohol / reminds me of university pre drinks memories | BZ44: no
A45: 22 | B45: b
A46: 23 | B46: a | C46: Sassy Good sassy song for the club Upbeat and empowering No, just like the song. Dont give connotations to songs or form a relationship to them because it will ruin the song if anything goes wrong. | D46: Sassy Good sassy song for the club / No, just like the song. | I46: Sassy Good sassy song for the club, Upbeat and empowering | M46: Upbeat and empowering | BH46: Sassy Good sassy song for the club | BR46: Sassy Good sassy song for the club / Upbeat and empowering | BZ46: No, just like the song. / Dont give connotations to songs or form a relationship to them because it will ruin the song if anything goes wrong
A47: 23 | B47: b | C47: Hatred Empowering Lyrics are powerful No, just like the song. Dont give connotations to songs or form a relationship to them because it will ruin the song if anything goes wrong | D47: No, just like the song. | I47: Hatred Empowering | J47: Lyrics are powerful | BZ47: No, just like the song. Dont give connotations to songs or form a relationship to them because it will ruin the song if anything goes wrong
A48: 24 | B48: a | C48: A solitary lonely man playing beautiful music for people. Bill Evans is one of the most prolific Jazz Players of all time, and came across him via his son, a film scorer, Evan Evans. Piece Peace has many different flavours within the song and beautifully describes Bill's emotions at the time of composition, no need for words. Yes. Discovered Bill Evans via his son, Evan Evans and recently downloaded it. I hope to discover more of his work soon. | D48: A solitary lonely man playing beautiful music for people. / Bill Evans is one of the most prolific Jazz Players of all time, and came across him via his son, a film scorer, Evan Evan / I hope to discover more of his work soon. | G48: Yes. Discovered Bill Evans via his son, Evan Evans and recently downloaded it. | K48: Piece Peace has many different flavours within the song and beautifully describes Bill's emotions at the time of composition, no need for words. | U48: Piece Peace has many different flavours within the song and beautifully describes Bill's emotions at the time of composition, no need for words. | V48: Piece Peace has many different flavours within the song and beautifully describes Bill's emotions at the time of composition, no need for words. | AA48: Bill Evans is one of the most prolific Jazz Players of all time, and came across him via his son, a film scorer, Evan Evan / Piece Peace has many different flavours within the song and beautifully describes Bill's emotions at the time of composition, no need for words. | AB48: Piece Peace has many different flavours within the song and beautifully describes Bill's emotions at the time of composition, no need for words. | AC48: Bill Evans is one of the most prolific Jazz Players of all time, and came across him via his son, a film scorer, Evan Evan | BM48: A solitary lonely man playing beautiful music for people
A49: 24 | B49: b | C49: A very basic yet effective pop melody. In my 20s, I would go out to see 1927 on a regular basis and fell in love with their music. They are reformed pop/rock band from the late 1980s. The flavour of the melody (regardless of the lyrics) gives me a high. Yes. This album was released after my partner died in 2012 and it has had a long term positive effective in my life in the grieving process. | D49: In my 20s, I would go out to see 1927 on a regular basis and fell in love with their music. They are reformed pop/rock band from the late 1980s. | G49: Yes. This album was released after my partner died in 2012 and it has had a long term positive effective in my life in the grieving process. | P49: A very basic yet effective pop melody. / The flavour of the melody (regardless of the lyrics) gives me a high/ \Like the tune.. reminds me of a fun night out | AA49: In my 20s, I would go out to see 1927 on a regular basis and fell in love with their music./ They are reformed pop/rock band from the late 1980s. | AB49: They are reformed pop/rock band from the late 1980s. | AC49: A very basic yet effective pop melody. / They are reformed pop/rock band from the late 1980s. | AR49: In my 20s, I would go out to see 1927 on a regular basis and fell in love with their music. | BA49: Yes. This album was released after my partner died in 2012 and it has had a long term positive effective in my life in the grieving process. | BB49: Yes. This album was released after my partner died in 2012 and it has had a long term positive effective in my life in the grieving process.
A50: 25 | B50: a | C50: Nostalgia, friends, sing along For the reasons mentioned above : Nostalgia, friends, sing along Makes me happy and reminds me of good times Just a song that I like. | D50: Just a song that I like. | AK50: Makes me happy and reminds me of good times | AR50: Makes me happy and reminds me of good times | AU50: Nostalgia, friends, sing along/ For the reasons mentioned above : Nostalgia, friends, sing along | AZ50: Nostalgia, friends, sing along/ For the reasons mentioned above : Nostalgia, friends, sing along | BI50: Nostalgia, friends, sing along/ For the reasons mentioned above : Nostalgia, friends, sing along | BR50: Makes me happy and reminds me of good times | BV50: Makes me happy and reminds me of good times
A51: 25 | B51: b | C51: Trying to learn this on guitar. Listening to friend playing this song and singing along in the back of a van during high school summer vacation. I like this song. Pretty. Like to sing along. Nostalgia. Like to sing along. Makes me happy. Just nostalgic I guess. | D51: I like this song. Pretty. | I51: Pretty | AP51: Listening to friend playing this song and singing along in the back of a van during high school summer vacation. | AR51: Listening to friend playing this song and singing along in the back of a van during high school summer vacation. | AU51: Nostalgia/ Just nostalgic I guess. | AV51: Trying to learn this on guitar | BC51: Listening to friend playing this song and singing along in the back of a van during high school summer vacation. | BI51: Like to sing along | BP51: Listening to friend playing this song and singing along in the back of a van during high school summer vacation. | BV51: Makes me happy.
A52: 26 | B52: a | C52: Its 'scherzo' like nature Great Cd Part of a fine album No | D52: Its 'scherzo' like nature Great Cd Part of a fine album | W52: Its 'scherzo' like nature | Z52: Part of a fine album | BZ52: No
A53: 26 | B53: b | C53: Happiness Makes me feel happy Happiness No - don't understand this question! | BV53: Happiness Makes me feel happy Happiness | BZ53: No - don't understand this question!
A54: 27 | B54: a | C54: musicals - friendship - story line and listen to the words I love musicals and rent is spectacular, not just for the phenomenal tracks for the meaning and characters the words and a great sing a long yes - musical theatre - studied and performed | D54: I love musicals and rent is spectacular, not just for the phenomenal tracks for the meaning and characters the words and a great sing a long | G54: yes - musical theatre - studied and performed | J54: musicals - friendship - story line and listen to the words / I love musicals and rent is spectacular, not just for the phenomenal tracks for the meaning and characters the words and a great sing a long | K54: musicals - friendship - story line and listen to the words / I love musicals and rent is spectacular, not just for the phenomenal tracks for the meaning and characters the words and a great sing a long | AC54: yes - musical theatre - studied and performed | AH54: musicals - friendship - story line and listen to the words / I love musicals and rent is spectacular, not just for the phenomenal tracks for the meaning and characters the words and a great sing a long | AV54: yes - musical theatre - studied and performed | AZ54: musicals - friendship - story line and listen to the words | BI54: I love musicals and rent is spectacular, not just for the phenomenal tracks for the meaning and characters the words and a great sing a long
A55: 27 | B55: b
A56: 28 | B56: a | C56: Easy listening song and artist Memory Lane listening, not my current favourite artist or style , but used to love Anne Murray not my current favourite artist or style , but used to love Anne Murray No. It's just an easy listening, background piece of music. | D56: artist Memory Lane listening, not my current favourite artist or style , but used to love Anne Murray not my current favourite artist or style , but used to love Anne Murray | F56: artist Memory Lane listening, not my current favourite artist or style , but used to love Anne Murray not my current favourite artist or style , but used to love Anne Murray | AA56: Easy listening song and artist / Memory Lane listening, not my current favourite artist or style , but used to love Anne Murray | AC56: Easy listening song and artist / No. It's just an easy listening, background piece of music. | BD56: No. It's just an easy listening, background piece of music. | BZ56: No. It's just an easy listening, background piece of music.
A57: 28 | B57: b | C57: my cousin, J I like this group, not necessarily my favourite track but selected a selection of their songs. The Ozarks were a favourite group of a cousin , who I loved, but who was tragically killed and I love listening to this group at anytime reminds me of him. No. Not this track in Particular but the group in general, | D57: I like this group, not necessarily my favourite track but selected a selection of their songs. | F57: I like this group, not necessarily my favourite track but selected a selection of their songs. | AA57: I like this group, not necessarily my favourite track but selected a selection of their songs./ The Ozarks were a favourite group of a cousin , who I loved, but who was tragically killed and I love listening to this group at anytime reminds me of him./ No. Not this track in Particular but the group in general, | AY57: my cousin, J / The Ozarks were a favourite group of a cousin , who I loved, but who was tragically killed and I love listening to this group at anytime reminds me of him. | BA57: The Ozarks were a favourite group of a cousin , who I loved, but who was tragically killed and I love listening to this group at anytime reminds me of him. | BZ57: No. Not this track in Particular but the group in general,
A58: 29 | B58: a | C58: It reminds me of the last time I listened to this band, about 2-3 years ago Because I love this band It's very relaxing music, and it's partly instrumental / partly in a language I don't understand (Czech) which makes it great for listening to when reading or thinking Yes, it reminds me of my life 2-3 years ago - which was completely different to it is now - which is when I last listened to it. | D58: Because I love this band It's very relaxing music, and it's partly instrumental / partly in a language I don't understand (Czech) which makes it great for listening to when reading or thinking | I58: Because I love this band It's very relaxing music | J58: partly in a language I don't understand (Czech) which makes it great for listening to when reading or thinking | O58: it's partly instrumental | AA58: It reminds me of the last time I listened to this band, about 2-3 years ago / Because I love this band It's very relaxing music, and it's partly instrumental / partly in a language I don't understand (Czech) which makes it great for listening to when reading or thinking | AR58: It reminds me of the last time I listened to this band, about 2-3 years ago / Yes, it reminds me of my life 2-3 years ago - which was completely different to it is now - which is when I last listened to it. | AT58: It reminds me of the last time I listened to this band, about 2-3 years ago / Yes, it reminds me of my life 2-3 years ago - which was completely different to it is now - which is when I last listened to it. | BL58: Because I love this band It's very relaxing music, and it's partly instrumental / partly in a language I don't understand (Czech) which makes it great for listening to when reading or thinking | BR58: Because I love this band It's very relaxing music, and it's partly instrumental / partly in a language I don't understand (Czech) which makes it great for listening to when reading or thinking | BT58: Because I love this band It's very relaxing music, and it's partly instrumental / partly in a language I don't understand (Czech) which makes it great for listening to when reading or thinking
A59: 29 | B59: b | C59: I love this song! It reminds me of when I saw this band live a couple months ago - they played it at the concert Because I have almost every other song by this band, but I didn't have this one yet, so I saved it I love this track because it's upbeat and I still haven't learned the words yet (it's in Swedish), which is a challenge because I'm still a beginner at Swedish Yes, I saw this band live a couple months ago and they played this song at the concert, and it was the first time I had ever heard it. Now every time I listen to it, it reminds me of dancing like crazy at the concert :) | D59: I love this song! | J59: I love this track because it's upbeat and I still haven't learned the words yet (it's in Swedish), which is a challenge because I'm still a beginner at Swedish | M59: Because I have almost every other song by this band, but I didn't have this one yet, so I saved it I love this track because it's upbeat and I still haven't learned the words yet (it's in Swedish), which is a challenge because I'm still a beginner at Swedish | AA59: It reminds me of when I saw this band live a couple months ago - they played it at the concert/ Because I have almost every other song by this band, but I didn't have this one yet, so I saved it | AL59: Yes, I saw this band live a couple months ago and they played this song at the concert, and it was the first time I had ever heard it. Now every time I listen to it, it reminds me of dancing like crazy at the concert :) | AN59: It reminds me of when I saw this band live a couple months ago - they played it at the concert/ Yes, I saw this band live a couple months ago and they played this song at the concert, and it was the first time I had ever heard it. Now every time I listen to it, it reminds me of dancing like crazy at the concert :) | BE59: Yes, I saw this band live a couple months ago and they played this song at the concert, and it was the first time I had ever heard it. Now every time I listen to it, it reminds me of dancing like crazy at the concert :)
A60: 30 | B60: a | C60: Relaxation/Calmness I found it a very fitting background noise whilst playing strategy games Artist's voice accompanied with the music is very soothing No, It is a good song but really, it's nothing extra special | D60: No, It is a good song but really, it's nothing extra special | F60: No, It is a good song but really, it's nothing extra special | I60: Relaxation/Calmness | V60: Artist's voice accompanied with the music is very soothing | Y60: Artist's voice accompanied with the music is very soothing | AA60: Artist's voice accompanied with the music is very soothing | BL60: I found it a very fitting background noise whilst playing strategy games | BS60: Relaxation/Calmness / Artist's voice accompanied with the music is very soothing | BT60: Relaxation/Calmness/ Artist's voice accompanied with the music is very soothing | BZ60: No, It is a good song but really, it's nothing extra special
A61: 30 | B61: b
A62: 31 | B62: a | C62: This track reminds me of warmth and summer. The first thing that comes to mind is a warm summer day and feeling the heat on my face. I found the song to be catchy and enjoyed the way it sounded. I like the voice of the singers. They have really great harmony. I also like the way the song sounds and it is uplifting and not depressing. It also makes me feel happy. Yes. I listened to this song while high on LSD and because of it this song is very special to me. | D62: I found the song to be catchy and enjoyed the way it sounded. / I like the voice of the singers. | I62: I found the song to be catchy and enjoyed the way it sounded. | U62: They have really great harmony | V62: I found the song to be catchy and enjoyed the way it sounded. / I also like the way the song sounds and it is uplifting and not depressing. | Y62: I like the voice of the singers. | AO62: Yes. I listened to this song while high on LSD and because of it this song is very special to me. | BM62: The first thing that comes to mind is a warm summer day and feeling the heat on my face. | BP62: This track reminds me of warmth and summer. / The first thing that comes to mind is a warm summer day and feeling the heat on my face. | BV62: It also makes me feel happy.
A63: 31 | B63: b | C63: Triumph I love Fleetwood Mac, and this song is iconic Fleetwood Mac. It's so catchy, and it makes me think I can do anything. I know all the words and can sing along. Stevie Nick's voice is awesome and she has to sing it with her ex which makes it even better. Also it's just an awesome song. Yes, I think I have a relationship with every one of Fleetwood Mac's song, but I think this one is especially important. It makes me think I can make it through changes, and that no matter what happens, things will be okay. | D63: Also it's just an awesome song. | G63: I know all the words and can sing along/ Yes, I think I have a relationship with every one of Fleetwood Mac's song, but I think this one is especially important. | I63: Triumph. It's so catchy, and it makes me think I can do anything. | J63: I know all the words and can sing along | K63: Triumph/ It's so catchy, and it makes me think I can do anything./ It makes me think I can make it through changes, and that no matter what happens, things will be okay. | Q63: Stevie Nick's voice is awesome and she has to sing it with her ex which makes it even better | AA63: I love Fleetwood Mac, and this song is iconic Fleetwood Mac. | BI63: I know all the words and can sing along
A64: 32 | B64: a | C64: Great track... One of my favourite bands, their latest album Not too loud just a nice, chilled song Not especially. | D64: Not too loud just a nice, chilled song | E64: Great track... One of my favourite bands, their latest album | I64: Not too loud just a nice, chilled song | V64: Not too loud just a nice, chilled song | Z64: Great track... One of my favourite bands, their latest album | AA64: Great track... One of my favourite bands, their latest album | BZ64: Not especially.
A65: 32 | B65: b | C65: Reminds me of the concert I attended last year Not too noisy, nice chilled song Brings back nice memories of the gig, a chilled but enjoyable song Yes, reminds me of a great concert and randomly bumping into an old friend that I hadn't seen in years | D65: Brings back nice memories of the gig, a chilled but enjoyable song | G65: Yes, reminds me of a great concert and randomly bumping into an old friend that I hadn't seen in years | I65: Brings back nice memories of the gig, a chilled but enjoyable song, Not too noisy, nice chilled song | V65: Not too noisy, nice chilled song | AN65: Reminds me of the concert I attended last year/ Brings back nice memories of the gig, a chilled but enjoyable song / Yes, reminds me of a great concert and randomly bumping into an old friend that I hadn't seen in years | AZ65: Yes, reminds me of a great concert and randomly bumping into an old friend that I hadn't seen in years
A66: 33 | B66: a | C66: University days, singing this at the top of our lungs at the end of a night out. I love it The memories associated with it yes Yes it reminds me of university days. | D66: I love it | AK66: The memories associated with it | AR66: University days, singing this at the top of our lungs at the end of a night out / Yes it reminds me of university days. | BH66: University days, singing this at the top of our lungs at the end of a night out | BI66: University days, singing this at the top of our lungs at the end of a night out
A67: 33 | B67: b | C67: Dancing I love it It motivates me especially when exercising. I love to listen to it when in the gym | D67: I love it It motivates me especially when exercising/ I love to listen to it when in the gym | BE67: Dancing | BG67: I love it It motivates me especially when exercising/ I love to listen to it when in the gym | BW67: I love it It motivates me especially when exercising
A68: 34 | B68: a | C68: The video game Guitar hero (as thats where i first heard the song) Its catchy to walk/travel to and is fairly neutral (doesnt really have any emotional connotations) Catchy/easy to time with walking pace No not really | I68: Its catchy to walk/travel to and is fairly neutral (doesnt really have any emotional connotations), catchy, easy to time with walking pace | K68: Its catchy to walk/travel to and is fairly neutral (doesnt really have any emotional connotations) | X68: Catchy/easy to time with walking pace | AE68: The video game Guitar hero (as thats where i first heard the song) | AL68: The video game Guitar hero (as thats where i first heard the song) | BK68: Its catchy to walk/travel to and is fairly neutral (doesnt really have any emotional connotations) / Catchy/easy to time with walking pace | BZ68: No not really
A69: 34 | B69: b
A70: 35 | B70: a | C70: PUMP UP THE BASS!!! It's my favorite song at the moment I enjoy listening to this song very much. Whenever I hear the song its like a wake up call and I'm filled with energy Im not completely sure what you mean by relationship | D70: I enjoy listening to this song very much. Whenever I hear the song its like a wake up call and I'm filled with energy | E70: It's my favorite song at the moment | L70: PUMP UP THE BASS!!! | BU70: I enjoy listening to this song very much. Whenever I hear the song its like a wake up call and I'm filled with energy | BW70: I enjoy listening to this song very much. Whenever I hear the song its like a wake up call and I'm filled with energy
A71: 35 | B71: b
A72: 36 | B72: a | C72: I saw them at SnowGlobe. I like the Chainsmokers. I heard them live and started listening to their music, and it reminds me of how much fun that music festival was. No, it doesn't particularly speak to me. | AA72: I saw them at SnowGlobe. I like the Chainsmokers./ I heard them live and started listening to their music, and it reminds me of how much fun that music festival was. | AM72: I heard them live and started listening to their music, and it reminds me of how much fun that music festival was. | AN72: I saw them at SnowGlobe. I like the Chainsmokers./ I heard them live and started listening to their music, and it reminds me of how much fun that music festival was. | BZ72: No, it doesn't particularly speak to me.
A73: 36 | B73: b | C73: It reminds me of high school in a good way. Because I fuck with G-Eazy heavy It gets me hyped up and reminds me of all the adventures I had in high school with my friends. Yes. I've listened to him since before he was big and he's from the same place I'm from. I saw him go from nothing to something and he raps about that in this song. | K73: Yes. I've listened to him since before he was big and he's from the same place I'm from. I saw him go from nothing to something and he raps about that in this song. | AA73: Because I fuck with G-Eazy heavy/ Yes. I've listened to him since before he was big and he's from the same place I'm from. I saw him go from nothing to something and he raps about that in this song. | AR73: It reminds me of high school in a good way./ It gets me hyped up and reminds me of all the adventures I had in high school with my friends. | AZ73: It gets me hyped up and reminds me of all the adventures I had in high school with my friends. | BR73: It gets me hyped up and reminds me of all the adventures I had in high school with my friends.
A74: 37 | B74: a | C74: Love the meld of music and voice. Enjoy the band and wanted to hear more of their stuff I love the sound, and find the lyrics intriguing. No, but I suspect I will. | D74: Enjoy the band and wanted to hear more of their stuff / I love the sound, and find the lyrics intriguing. | J74: I love the sound, and find the lyrics intriguing. | U74: Love the meld of music and voice. | V74: Love the meld of music and voice. / I love the sound, and find the lyrics intriguing. | Y74: Love the meld of music and voice. | AA74: Enjoy the band and wanted to hear more of their stuff | BZ74: No, but I suspect I will.
A75: 37 | B75: b | C75: Dreary and dirge like. I wanted to explore more of Whitaker's music I found it tedious. It couldn't quite make up its mind what it wanted to be. The mood kept shifting. No, this is the first time I've heard it. | H75: No, this is the first time I've heard it. | I75: Dreary and dirge like., I wanted to explore more of Whitaker's music I found it tedious | V75: Dreary and dirge like./ It couldn't quite make up its mind what it wanted to be. | AA75: wanted to explore more of Whitaker's music | BR75: The mood kept shifting. | BZ75: No, this is the first time I've heard it.
A76: 38 | B76: a | C76: My boyfriend I have all of Beyonce's music saved but this is one of my favourites. I think the lyrics are really meaningful and poetic. It has Prince vibes, who is another artist I love. Yes. It was playing when my boyfriend first told me he loved me. Seeing her perform it live was beautiful too. I cried. | E76: My boyfriend I have all of Beyonce's music saved but this is one of my favourites. | G76: Yes. It was playing when my boyfriend first told me he loved me. Seeing her perform it live was beautiful too. I cried. | J76: I think the lyrics are really meaningful and poetic. | K76: I think the lyrics are really meaningful and poetic. | AA76: My boyfriend I have all of Beyonce's music saved but this is one of my favourites. | AN76: Yes. It was playing when my boyfriend first told me he loved me. Seeing her perform it live was beautiful too. I cried. | AO76: It was playing when my boyfriend first told me he loved me. | BB76: My boyfriend I have all of Beyonce's music saved but this is one of my favourites. | BX76: It was playing when my boyfriend first told me he loved me. Seeing her perform it live was beautiful too. I cried.
A77: 38 | B77: b | C77: Trainspotting. The anticipatory opening. It was part of a soundtrack playlist from my favourite movies. It makes me excited, the beat picks me up. I kinda want to run or jump around to it. Not particularly. Like I said, it is from one of my favourite films trainspotting but other than that I don't relate to it much. | M77: It makes me excited, the beat picks me up. | AF77: Trainspotting. The anticipatory opening./ It was part of a soundtrack playlist from my favourite movies/ Not particularly. Like I said, it is from one of my favourite films trainspotting but other than that I don't relate to it much. | AI77: It was part of a soundtrack playlist from my favourite movies | BE77: I kinda want to run or jump around to it. | BU77: It makes me excited, the beat picks me up. | BZ77: Not particularly. Like I said, it is from one of my favourite films trainspotting but other than that I don't relate to it much.
A78: 39 | B78: a | C78: The intro is very haunting so I picture a dark club with red lights that flicker through the club.. I love BeyoncÃ©.. her music makes me feel like anything is possible.. makes me fee more positive and stronger about myself. The song is about a girl who works her hardest and pushes her self to numerous limits so she can get the best out of life but it's never enough.. So somehow it's pushing me to go finish my degree and work my hardest to get the life I want.. however it is sang in quite a sexual manner so people's views about the song may differ.. Not sure.. It's simply a powerful song | D78: I love BeyoncÃ©.. her music makes me feel like anything is possible.. makes me fee more positive and stronger about myself. | I78: it is sang in quite a sexual manner so people's views about the song may differ, It's simply a powerful song | K78: The song is about a girl who works her hardest and pushes her self to numerous limits so she can get the best out of life but it's never enough.. So somehow it's pushing me to go finish my degree and work my hardest to get the life I want.. however it is sang in quite a sexual manner so people's views about the song may differ.. Not sure.. It's simply a powerful song | AA78: I love BeyoncÃ©.. her music makes me feel like anything is possible.. makes me fee more positive and stronger about myself. | BM78: The intro is very haunting so I picture a dark club with red lights that flicker through the club.. / The song is about a girl who works her hardest and pushes her self to numerous limits so she can get the best out of life but it's never enough.. So somehow it's pushing me to go finish my degree and work my hardest to get the life I want.. however it is sang in quite a sexual manner so people's views about the song may differ.. Not sure.. It's simply a powerful song | BR78: I love BeyoncÃ©.. her music makes me feel like anything is possible.. makes me fee more positive and stronger about myself. / | BV78: I love BeyoncÃ©.. her music makes me feel like anything is possible.. makes me fee more positive and stronger about myself. | BW78: The song is about a girl who works her hardest and pushes her self to numerous limits so she can get the best out of life but it's never enough.. So somehow it's pushing me to go finish my degree and work my hardest to get the life I want.. however it is sang in quite a sexual manner so people's views about the song may differ.. Not sure.. It's simply a powerful song | BZ78: Not sure.. It's simply a powerful song
A79: 39 | B79: b | C79: I think about the first moment when you supposedly meet the love of your life and you say 'hello'.. Again.. I love BeyoncÃ© and majority if not all of her music.. It kind of gives me hope.. that there could be a moment in life when you meet the person that you're supposed to be with and you might know by simply saying 'hello' Not sure.. haven't found that person yet.. so maybe when I do I'll have a relationship with this son because I'll understand better what she means. | D79: Again.. I love BeyoncÃ© and majority if not all of her music.. | AA79: Again.. I love BeyoncÃ© and majority if not all of her music.. | BM79: I think about the first moment when you supposedly meet the love of your life and you say 'hello'.. that there could be a moment in life when you meet the person that you're supposed to be with and you might know by simply saying 'hello' Not sure.. haven't found that person yet.. so maybe when I do I'll have a relationship with this son because I'll understand better what she means. | BV79: It kind of gives me hope.. | BZ79: that there could be a moment in life when you meet the person that you're supposed to be with and you might know by simply saying 'hello' Not sure.. haven't found that person yet.. so maybe when I do I'll have a relationship with this son because I'll understand better what she means.
A80: 40 | B80: a | C80: It reminds me of singing at Christmas time and my childhood in a choir. /Good memories singing /Good memories, pleasant music/Yes - it is a piece I sang many times as a child | D80: /Good memories singing /Good memories, pleasant music | G80: Yes - it is a piece I sang many times as a child | AK80: Good memories singing, | AR80: It reminds me of singing at Christmas time and my childhood in a choir. / Yes - it is a piece I sang many times as a child | AV80: It reminds me of singing at Christmas time and my childhood in a choir. / Yes - it is a piece I sang many times as a child | BO80: It reminds me of singing at Christmas time and my childhood in a choir.
A81: 40 | B81: b | C81: Christmas\The album was a gift\I don't really like this version of silent night. It is a bit too polite. \No. It just happens to be on an album that was given to me. | F81: \I don't really like this version of silent night. It is a bit too polite | I81: It is a bit too polite | Z81: The album was a gift/ No. It just happens to be on an album that was given to me. | AD81: \I don't really like this version of silent night. It is a bit too polite | AS81: The album was a gift , It just happens to be on an album that was given to me. | BO81: Christmas | BZ81: No. It just happens to be on an album that was given to me.
A82: 41 | B82: a | C82: Dancing in a pub/Because it pleases me/Because I love the song/tes | D82: Because it pleases me/Because I love the song | G82: tes | BE82: Dancing in a pub | BH82: Dancing in a pub
A83: 41 | B83: b | C83: Cold time \Mood of the track\Beacuse it is charming\yes | G83: yes | I83: Beacuse it is charming | K83: Mood of the track\Beacuse it is charming | BN83: Cold time
A84: 42 | B84: a | C84: Seeing them in concert /So I can run to it /I enjoy this track during running as it is very upbeat /Not really it's just a motivator | D84: I enjoy this track during running as it is very upbeat | M84: I enjoy this track during running as it is very upbeat | AA84: Seeing them in concert | AN84: Seeing them in concert | BG84: /So I can run to it / I enjoy this track during running as it is very upbeat | BW84: Not really it's just a motivator | BZ84: Not really it's just a motivator
A85: 42 | B85: b | C85: Revision playlist \I like the whole album which was uploaded including this song \It's a good uplifting sing a long song \No its just enjoyable to listen to | D85: No its just enjoyable to listen to | I85: Uplifting | Z85: \I like the whole album which was uploaded including this song | AI85: Revision playlist | BI85: It's a good uplifting sing a long song | BL85: Revision playlist | BR85: It's a good uplifting sing a long song | BZ85: No its just enjoyable to listen to
A86: 43 | B86: a | C86: Ah, not quite what I fancied just now.... can't remember -- it's part of a playlist I made many years ago but still return to often. It's quite an eclectic mix of tracks in the playlist ... this gives a bit of downtime ... it's very beautiful ... has 'missing' inner parts in the harmony that I can add for myself ... not particularly ... If I stop to think about it I can associate events with it (playing it on the piano at home, listening to it in a concert once half a life-time ago, and imagining the performer groaning his way through some of the other tracks on the disc) but I don't usually pay it so much attention! | F86: Ah, not quite what I fancied just now.... | I86: this gives a bit of downtime ... it's very beautiful | U86: has 'missing' inner parts in the harmony that I can add for myself ... | AA86: not particularly ... If I stop to think about it I can associate events with it (playing it on the piano at home, listening to it in a concert once half a life-time ago, and imagining the performer groaning his way through some of the other tracks on the disc) but I don't usually pay it so much attention! | AI86: can't remember -- it's part of a playlist I made many years ago but still return to often. / It's quite an eclectic mix of tracks in the playlist ... this gives a bit of downtime ... it's very beautiful ... has 'missing' inner parts in the harmony that I can add for myself ... | AN86: not particularly ... If I stop to think about it I can associate events with it (playing it on the piano at home, listening to it in a concert once half a life-time ago, and imagining the performer groaning his way through some of the other tracks on the disc) but I don't usually pay it so much attention! | AO86: not particularly ... If I stop to think about it I can associate events with it (playing it on the piano at home, listening to it in a concert once half a life-time ago, and imagining the performer groaning his way through some of the other tracks on the disc) but I don't usually pay it so much attention! | AV86: not particularly ... If I stop to think about it I can associate events with it (playing it on the piano at home, listening to it in a concert once half a life-time ago, and imagining the performer groaning his way through some of the other tracks on the disc) but I don't usually pay it so much attention! | BM86: imagining the performer groaning his way through some of the other tracks on the disc) | BZ86: not particularly ... If I stop to think about it I can associate events with it (playing it on the piano at home, listening to it in a concert once half a life-time ago, and imagining the performer groaning his way through some of the other tracks on the disc) but I don't usually pay it so much attention!
A87: 43 | B87: b | C87: Unusual to have another classical track picked out (relatively few are classical in this playlist) I love string quartets .... shostakovich 8 is one I've played ... I would actually say my level of enjoyment of the track varies quite a bit -- I love the sense of a small group of people pulling together... on the other hand it can be a bit distracting if I'm listening in the background while doing something else. Yes, I suppose so -- had a great evening busking through string quartets with friends not that long after my mum died -- seemed the first time I'd really connected with people well and I appreciated that sense of support. | D87: I love string quartets .... shostakovich 8 is one I've played ../ I would actually say my level of enjoyment of the track varies quite a bit -- I love the sense of a small group of people pulling together... on the other hand it can be a bit distracting if I'm listening in the background while doing something else. | F87: I would actually say my level of enjoyment of the track varies quite a bit -- I love the sense of a small group of people pulling together... on the other hand it can be a bit distracting if I'm listening in the background while doing something else. | K87: I would actually say my level of enjoyment of the track varies quite a bit -- I love the sense of a small group of people pulling together... on the other hand it can be a bit distracting if I'm listening in the background while doing something else. | AC87: Unusual to have another classical track picked out (relatively few are classical in this playlist) | AV87: I love string quartets .... shostakovich 8 is one I've played ../ Yes, I suppose so -- had a great evening busking through string quartets with friends not that long after my mum died -- seemed the first time I'd really connected with people well and I appreciated that sense of support. | AZ87: Yes, I suppose so -- had a great evening busking through string quartets with friends not that long after my mum died -- seemed the first time I'd really connected with people well and I appreciated that sense of support. | BA87: Yes, I suppose so -- had a great evening busking through string quartets with friends not that long after my mum died -- seemed the first time I'd really connected with people well and I appreciated that sense of support.
A88: 44 | B88: a | C88: It reminds me of my best friend throughout high school as we both loved Aerosmith and always used to sing along to their songs. Because it's a really fun song to listen to when played nice and loud! I enjoy it because it's really powerful and fun to sing (or screech out of tune) along with without caring about who's listening! Yes - the band reminds me of my best friend from high school and the many times we spent listening and singing along to Aerosmith and playing their songs on guitar hero on the Wii! | D88: It reminds me of my best friend throughout high school as we both loved Aerosmith and always used to sing along to their songs. / I enjoy it because it's really powerful and fun to sing (or screech out of tune) along with without caring about who's listening! | G88: Yes - the band reminds me of my best friend from high school and the many times we spent listening and singing along to Aerosmith and playing their songs on guitar hero on the Wii! | V88: Because it's a really fun song to listen to when played nice and loud! | AA88: It reminds me of my best friend throughout high school as we both loved Aerosmith and always used to sing along to their songs. / Yes - the band reminds me of my best friend from high school and the many times we spent listening and singing along to Aerosmith and playing their songs on guitar hero on the Wii! | AE88: the band reminds me of my best friend from high school and the many times we spent listening and singing along to Aerosmith and playing their songs on guitar hero on the Wii! | AO88: Yes - the band reminds me of my best friend from high school and the many times we spent listening and singing along to Aerosmith and playing their songs on guitar hero on the Wii! | AR88: It reminds me of my best friend throughout high school as we both loved Aerosmith and always used to sing along to their songs. / Yes - the band reminds me of my best friend from high school and the many times we spent listening and singing along to Aerosmith and playing their songs on guitar hero on the Wii! | AZ88: It reminds me of my best friend throughout high school as we both loved Aerosmith and always used to sing along to their songs. / Yes - the band reminds me of my best friend from high school and the many times we spent listening and singing along to Aerosmith and playing their songs on guitar hero on the Wii! | BI88: It reminds me of my best friend throughout high school as we both loved Aerosmith and always used to sing along to their songs. / I enjoy it because it's really powerful and fun to sing (or screech out of tune) along with without caring about who's listening! | BQ88: I enjoy it because it's really powerful and fun to sing (or screech out of tune) along with without caring about who's listening!
A89: 44 | B89: b | C89: It makes me think of being outside and having fun in summer. I used it to choreograph a dance to when I was the tap teacher in my university dance society. It's really upbeat so it puts me in a good mood. It's an easy song to sing along with as well. Yes to an extent, as it reminds me of my time as a tap teacher. | G89: Yes to an extent, as it reminds me of my time as a tap teacher. | M89: It's really upbeat so it puts me in a good mood. | AM89: It makes me think of being outside and having fun in summer. | AR89: I used it to choreograph a dance to when I was the tap teacher in my university dance society./ Yes to an extent, as it reminds me of my time as a tap teacher. | BE89: I used it to choreograph a dance to when I was the tap teacher in my university dance society. | BP89: It makes me think of being outside and having fun in summer. | BR89: It's really upbeat so it puts me in a good mood. | BV89: It's really upbeat so it puts me in a good mood.
A90: 45 | B90: a | C90: Dancing /Lovely uplifting music that creates a good mood and happy that makes me want to dance/I enjoy the track - mentioned above. The fast beat and cheerful voice/No just enjoy listening to the album | D90: I enjoy the track - mentioned above. / No just enjoy listening to the album | I90: Lovely uplifting music | M90: The fast beat and cheerful voice | X90: The fast beat and cheerful voice | Y90: The fast beat and cheerful voice | Z90: No just enjoy listening to the album | BE90: Dancing | BR90: Lovely uplifting music that creates a good mood and happy that makes me want to dance | BV90: Lovely uplifting music that creates a good mood and happy that makes me want to dance | BZ90: No just enjoy listening to the album
A91: 45 | B91: b | C91: Sam smith and the James Bond film theme song \I down loaded the album as I enjoyed 2 tracks \Well it is a album/ song I enjoy when I want to relax. I usually skip the track when I am driving as I feel I cannot sing a long. \No it is a album track that I have acquired by opportunity | Z91: \I down loaded the album as I enjoyed 2 tracks / Well it is a album/ song I enjoy when I want to relax./ o it is a album track that I have acquired by opportunity | AA91: Sam smith and the James Bond film theme song | AF91: Sam smith and the James Bond film theme song | BF91: I usually skip the track when I am driving as I feel I cannot sing a long. | BI91: I usually skip the track when I am driving as I feel I cannot sing a long. | BY91: Well it is a album/ song I enjoy when I want to relax. | BZ91: No it is a album track that I have acquired by opportunity
A92: 46 | B92: a | C92: Relaxing, contemplative, interesting pleasing drum line, prayerful, emotional cello and violins /A favorite artist and track. Makes me feel good to listen to. Wanted to share with friends of like taste./See above. Makes me feel relaxed. Evokes a calm emotional response. Interesting from a musical standpoint. Spirtual content./Modern rendition of traditional hymn which I have heard for years. | E92: A favorite artist and track. | G92: Modern rendition of a traditional hymn that I have heard for years | I92: Relaxing, contemplative, interesting, pleasing drum line, emotional cello and violins | K92: Relaxing, contemplative, interesting pleasing drum line, prayerful, emotional cello and violins / Spirtual content. | M92: Relaxing, contemplative, interesting pleasing drum line, prayerful, emotional cello and violins / | O92: Relaxing, contemplative, interesting pleasing drum line, prayerful, emotional cello and violins / | U92: Interesting from a musical standpoint. | AA92: A favorite artist and track. | AD92: Modern rendition of traditional hymn which I have heard for years. | AZ92: Wanted to share with friends of like taste. | BR92: Makes me feel good to listen to. | BS92: Relaxing, contemplative, interesting pleasing drum line, prayerful, emotional cello and violins / Makes me feel relaxed. Evokes a calm emotional response. | BT92: Makes me feel relaxed. Evokes a calm emotional response. | BV92: Makes me feel good to listen to.
A93: 46 | B93: b | C93: Pleasing prayerful\A favorite artist and track I wanted to recall as mybest of\Lyric is prayerful spiritual conversation and the artists words become my own. The musical arrangement is dreamy with cello piano and lead guitar with vibrato. Great tasty drumming.\It is a spiritual faith based song which resonates with my spiritual sensibilities. | D93: Great tasty drumming | E93: A favorite artist and track I wanted to recall as mybest of | I93: Pleasing prayerful, It is a spiritual faith based song, The musical arrangement is dreamy | J93: Lyric is prayerful spiritual conversation and the artists words become my own. | K93: Pleasing prayerful/ It is a spiritual faith based song which resonates with my spiritual sensibilities. | O93: he musical arrangement is dreamy with cello piano and lead guitar with vibrato. Great tasty drumming. | AA93: A favorite artist and track I wanted to recall as mybest of/ Lyric is prayerful spiritual conversation and the artists words become my own. | BY93: resonates with my spiritual sensibilities
A94: 47 | B94: a | C94: Good song, haven't heard it for a while!/I have all of The Beatles' albums saved because they're obviously amazing./It's a very good song that I haven't heard for a while./Not really. | D94: Good song, haven't heard it for a while! / /I have all of The Beatles' albums saved because they're obviously amazing. / It's a very good song that I haven't heard for a while | Z94: /I have all of The Beatles' albums saved because they're obviously amazing. | AA94: /I have all of The Beatles' albums saved because they're obviously amazing. | AT94: Good song, haven't heard it for a while! | BZ94: Not really
A95: 47 | B95: b | C95: One of my favourite songs.\It's a band and an album that I really like.\It's the sort of music that I like.\A bit, it's quite an emotional song for me that has some good memories attached. | D95: It's a band and an album that I really like. | E95: One of my favourite songs. | I95: it's quite an emotional song | Z95: It's a band and an album that I really like. | AA95: It's a band and an album that I really like. | AC95: \It's the sort of music that I like. | AK95: has some good memories attached. | AM95: A bit, it's quite an emotional song for me that has some good memories attached. | BZ95: A bit, it's quite an emotional song for me that has some good memories attached.
A96: 48 | B96: a | C96: The sadness of drinking too much- the song is about alcoholism/I didn't- when I plugged my iPod into my computer I chose the option "fill available space with random songs" and this was one of them/The guitar solo, the lyrics and the vocals suggest that Roger Daltrey is descending into madness. The track is also musically similar in parts to other Who tracks from that period/Yes, because I think I've seen The Who perform it live and all the energy their live shows bring. | J96: The guitar solo, the lyrics and the vocals suggest that Roger Daltrey is descending into madness. | K96: The sadness of drinking too much- the song is about alcoholism / The guitar solo, the lyrics and the vocals suggest that Roger Daltrey is descending into madness. | O96: The guitar solo, the lyrics and the vocals suggest that Roger Daltrey is descending into madness. | U96: The track is also musically similar in parts to other Who tracks from that period | Y96: The guitar solo, the lyrics and the vocals suggest that Roger Daltrey is descending into madness. | AA96: The guitar solo, the lyrics and the vocals suggest that Roger Daltrey is descending into madness./ The track is also musically similar in parts to other Who tracks from that period/ Yes, because I think I've seen The Who perform it live and all the energy their live shows bring. | AB96: The track is also musically similar in parts to other Who tracks from that period | AD96: Yes, because I think I've seen The Who perform it live and all the energy their live shows bring. | AI96: I didn't- when I plugged my iPod into my computer I chose the option "fill available space with random songs" and this was one of them | AL96: I didn't- when I plugged my iPod into my computer I chose the option "fill available space with random songs" and this was one of them | AN96: Yes, because I think I've seen The Who perform it live and all the energy their live shows bring.
A97: 48 | B97: b | C97: It's a bit average\I didn't add it, it was one of the random songs/ tracks added to my iPod by iTunes \This is the first time I've actively listened to it. Based on this first listen it's clearly an album filler. Lyrically and musically it's uninspired \No- it's the first time I've listened to it actively | F97: It's a bit average/ Based on this first listen it's clearly an album filler./ Lyrically and musically it's uninspired | H97: This is the first time I've actively listened to it. / \No- it's the first time I've listened to it actively | J97: Lyrically and musically it's uninspired | U97: Lyrically and musically it's uninspired | AE97: tracks added to my iPod by iTunes | BZ97: \No- it's the first time I've listened to it actively
A98: 49 | B98: a | C98: Spinning in a field- arms out enjoying the sun/The cheerful tune and the overall message made me happy/It always bring a smile to my face and makes me want to dance/No, I haven't done anything specifically other than listen to it | I98: cheerful | J98: The cheerful tune and the overall message made me happy | K98: The cheerful tune and overall message made me happy | P98: The cheerful tune and the overall message made me happy | BE98: It always bring a smile to my face and makes me want to dance | BM98: Spinning in a field- arms out enjoying the sun | BN98: Spinning in a field- arms out enjoying the sun | BV98: The cheerful tune and the overall message made me happy/ It always bring a smile to my face and makes me want to dance | BZ98: No, I haven't done anything specifically other than listen to it
A99: 49 | B99: b | C99: It makes me think about Harry Potter\The beat is really enjoyable and I really like the lyrics\Because it is really easy to sing to and is just enjoyable to listen to more than once\No, I haven't done anything with this music before | D99: The beat is really enjoyable and I really like the lyrics/ Because it is really easy to sing to and is just enjoyable to listen to more than once | J99: The beat is really enjoyable and I really like the lyrics | M99: The beat is really enjoyable and I really like the lyrics | AF99: It makes me think about Harry Potter | BI99: Because it is really easy to sing to and is just enjoyable to listen to more than once | BZ99: No, I haven't done anything with this music before
A100: 50 | B100: a | C100: My 14-year-old self who just bought this album. /I have been a fan of this band for over a decade now, and I can't imagine not having at least some songs of this artist on my device. /The track is lively and powerful, and is sung by one of my favourite vocalists. I also like the combination of string quartet and the typical metal band set-up (i.e. the melodic and rhythmic aspects of this song). /Yes. I bought this album when I was just becoming familiar with the metal genre, and the songs from this album remind me of my time in secondary school and the positive emotions I associate with that time. | D100: The track is lively and powerful, and is sung by one of my favourite vocalists. I also like the combination of string quartet and the typical metal band set-up (i.e. the melodic and rhythmic aspects of this song). | G100: Yes. I bought this album when I was just becoming familiar with the metal genre, and the songs from this album remind me of my time in secondary school and the positive emotions I associate with that time. | I100: The track is lively and powerful | O100: The track is lively and powerful, and is sung by one of my favourite vocalists. I also like the combination of string quartet and the typical metal band set-up (i.e. the melodic and rhythmic aspects of this song). | P100: The track is lively and powerful, and is sung by one of my favourite vocalists. I also like the combination of string quartet and the typical metal band set-up (i.e. the melodic and rhythmic aspects of this song). | S100: The track is lively and powerful, and is sung by one of my favourite vocalists. I also like the combination of string quartet and the typical metal band set-up (i.e. the melodic and rhythmic aspects of this song). | Y100: The track is lively and powerful, and is sung by one of my favourite vocalists. I also like the combination of string quartet and the typical metal band set-up (i.e. the melodic and rhythmic aspects of this song). | Z100: My 14-year-old self who just bought this album./ Yes. I bought this album when I was just becoming familiar with the metal genre, and the songs from this album remind me of my time in secondary school and the positive emotions I associate with that time. | AA100: I have been a fan of this band for over a decade now, and I can't imagine not having at least some songs of this artist on my device. | AC100: Yes. I bought this album when I was just becoming familiar with the metal genre, and the songs from this album remind me of my time in secondary school and the positive emotions I associate with that time. | AM100: Yes. I bought this album when I was just becoming familiar with the metal genre, and the songs from this album remind me of my time in secondary school and the positive emotions I associate with that time. | AR100: My 14-year-old self who just bought this album./ Yes. I bought this album when I was just becoming familiar with the metal genre, and the songs from this album remind me of my time in secondary school and the positive emotions I associate with that time. | AU100: Yes. I bought this album when I was just becoming familiar with the metal genre, and the songs from this album remind me of my time in secondary school and the positive emotions I associate with that time.
...

Sheet ALL_Level 3 
A1: Participant Number | B1: Track ID | C1: Positive | D1: Favourite | E1: Negative | F1: Familiar | G1: Unfamiliar | H1: Musical Expressive Characteristics | I1: Lyrics | J1: Musical Meaning | K1: Bass Line | L1: Beat | M1: Hook | N1: Instrumentation | O1: Melody | P1: Performer | Q1: Production | R1: Rhythm | S1: Riffs-Ornamentation | T1: Song Structure/Composition | U1: Sound | V1: Style | W1: Tempo | X1: Vocals | Y1: Album | Z1: Artist | AA1: Era | AB1: Genre | AC1: Version | AD1: Other Forms of Media | AE1: Film | AF1: Music Video | AG1: Musical | AH1: Playlist | AI1: Television | AJ1: Memory | AK1: Discovery | AL1: Emotion | AM1: Event/Concert | AN1: Personal Event | AO1: Vacation | AP1: Place | AQ1: Time or Stage in Life | AR1: Girft/Recommendation | AS1: Rediscovery | AT1: Reminisce- Nostalgia | AU1: Personal Performance | AV1: People | AW1: Being Alone | AX1: Family | AY1: Friends | AZ1: Loss of a person | BA1: Romantic relationship | BB1: Recommendation from Friend/Family | BC1: Accompaniment | BD1: Dancing | BE1: Driving | BF1: Exercising | BG1: Partying | BH1: Singing | BI1: Sleeping | BJ1: Walking | BK1: Working | BL1: Imagination | BM1: Season/time of day/weather | BN1: Christmas | BO1: Summer | BP1: Create Atmosphere | BQ1: Change Mood | BR1: Stress/Frustration/Tension | BS1: Calm | BT1: Energy | BU1: Happiness-good mood | BV1: Motivation/focus | BW1: Sadness | BX1: Match Mood | BY1: No relationship | BZ1: Participating in the study
A2: 1 | B2: a | C2: 1 | D2: 0 | E2: 0 | F2: 0 | G2: 0 | H2: 0 | I2: 0 | J2: 0 | K2: 0 | L2: 0 | M2: 0 | N2: 0 | O2: 0 | P2: 0 | Q2: 0 | R2: 0 | S2: 0 | T2: 0 | U2: 0 | V2: 0 | W2: 0 | X2: 0 | Y2: 1 | Z2: 1 | AA2: 0 | AB2: 0 | AC2: 0 | AD2: 0 | AE2: 0 | AF2: 0 | AG2: 0 | AH2: 0 | AI2: 0 | AJ2: 0 | AK2: 0 | AL2: 0 | AM2: 0 | AN2: 0 | AO2: 0 | AP2: 0 | AQ2: 1 | AR2: 0 | AS2: 0 | AT2: 0 | AU2: 0 | AV2: 0 | AW2: 0 | AX2: 0 | AY2: 0 | AZ2: 0 | BA2: 0 | BB2: 0 | BC2: 0 | BD2: 0 | BE2: 0 | BF2: 0 | BG2: 0 | BH2: 0 | BI2: 0 | BJ2: 0 | BK2: 0 | BL2: 0 | BM2: 0 | BN2: 0 | BO2: 0 | BP2: 0 | BQ2: 0 | BR2: 0 | BS2: 0 | BT2: 0 | BU2: 0 | BV2: 0 | BW2: 0 | BX2: 0 | BY2: 0 | BZ2: 0
A3: 1 | B3: b | C3: 0 | D3: 0 | E3: 0 | F3: 0 | G3: 1 | H3: 0 | I3: 0 | J3: 0 | K3: 0 | L3: 0 | M3: 0 | N3: 0 | O3: 0 | P3: 0 | Q3: 0 | R3: 0 | S3: 0 | T3: 0 | U3: 0 | V3: 0 | W3: 0 | X3: 0 | Y3: 0 | Z3: 0 | AA3: 0 | AB3: 0 | AC3: 0 | AD3: 0 | AE3: 0 | AF3: 0 | AG3: 0 | AH3: 0 | AI3: 0 | AJ3: 0 | AK3: 0 | AL3: 0 | AM3: 0 | AN3: 0 | AO3: 0 | AP3: 0 | AQ3: 0 | AR3: 0 | AS3: 0 | AT3: 0 | AU3: 0 | AV3: 0 | AW3: 0 | AX3: 0 | AY3: 0 | AZ3: 0 | BA3: 0 | BB3: 0 | BC3: 0 | BD3: 0 | BE3: 0 | BF3: 0 | BG3: 0 | BH3: 0 | BI3: 0 | BJ3: 0 | BK3: 0 | BL3: 0 | BM3: 0 | BN3: 0 | BO3: 0 | BP3: 0 | BQ3: 0 | BR3: 0 | BS3: 0 | BT3: 0 | BU3: 0 | BV3: 0 | BW3: 0 | BX3: 0 | BY3: 1 | BZ3: 0
A4: 2 | B4: a | C4: 1 | D4: 0 | E4: 0 | F4: 0 | G4: 0 | H4: 0 | I4: 1 | J4: 0 | K4: 0 | L4: 0 | M4: 0 | N4: 0 | O4: 0 | P4: 0 | Q4: 0 | R4: 0 | S4: 0 | T4: 1 | U4: 0 | V4: 1 | W4: 0 | X4: 1 | Y4: 0 | Z4: 1 | AA4: 0 | AB4: 1 | AC4: 0 | AD4: 0 | AE4: 0 | AF4: 0 | AG4: 0 | AH4: 0 | AI4: 0 | AJ4: 0 | AK4: 0 | AL4: 1 | AM4: 1 | AN4: 0 | AO4: 0 | AP4: 0 | AQ4: 0 | AR4: 0 | AS4: 0 | AT4: 0 | AU4: 0 | AV4: 0 | AW4: 0 | AX4: 0 | AY4: 0 | AZ4: 0 | BA4: 0 | BB4: 0 | BC4: 0 | BD4: 0 | BE4: 0 | BF4: 0 | BG4: 0 | BH4: 0 | BI4: 0 | BJ4: 0 | BK4: 0 | BL4: 0 | BM4: 0 | BN4: 0 | BO4: 0 | BP4: 0 | BQ4: 0 | BR4: 0 | BS4: 0 | BT4: 0 | BU4: 0 | BV4: 0 | BW4: 0 | BX4: 0 | BY4: 1 | BZ4: 0
A5: 2 | B5: b | C5: 1 | D5: 0 | E5: 0 | F5: 0 | G5: 0 | H5: 0 | I5: 0 | J5: 1 | K5: 0 | L5: 0 | M5: 0 | N5: 0 | O5: 0 | P5: 1 | Q5: 0 | R5: 0 | S5: 0 | T5: 0 | U5: 0 | V5: 0 | W5: 0 | X5: 1 | Y5: 1 | Z5: 1 | AA5: 0 | AB5: 1 | AC5: 0 | AD5: 0 | AE5: 0 | AF5: 0 | AG5: 0 | AH5: 0 | AI5: 0 | AJ5: 0 | AK5: 0 | AL5: 0 | AM5: 1 | AN5: 0 | AO5: 0 | AP5: 0 | AQ5: 0 | AR5: 0 | AS5: 0 | AT5: 0 | AU5: 0 | AV5: 0 | AW5: 0 | AX5: 0 | AY5: 0 | AZ5: 0 | BA5: 0 | BB5: 0 | BC5: 0 | BD5: 0 | BE5: 0 | BF5: 0 | BG5: 0 | BH5: 0 | BI5: 0 | BJ5: 0 | BK5: 0 | BL5: 0 | BM5: 0 | BN5: 0 | BO5: 0 | BP5: 0 | BQ5: 0 | BR5: 0 | BS5: 0 | BT5: 0 | BU5: 0 | BV5: 0 | BW5: 0 | BX5: 0 | BY5: 0 | BZ5: 0
A6: 3 | B6: a | C6: 0 | D6: 0 | E6: 0 | F6: 0 | G6: 0 | H6: 1 | I6: 1 | J6: 1 | K6: 0 | L6: 1 | M6: 0 | N6: 0 | O6: 0 | P6: 0 | Q6: 0 | R6: 0 | S6: 0 | T6: 0 | U6: 0 | V6: 0 | W6: 0 | X6: 0 | Y6: 0 | Z6: 0 | AA6: 0 | AB6: 0 | AC6: 0 | AD6: 0 | AE6: 0 | AF6: 0 | AG6: 0 | AH6: 0 | AI6: 0 | AJ6: 0 | AK6: 0 | AL6: 0 | AM6: 0 | AN6: 0 | AO6: 0 | AP6: 0 | AQ6: 0 | AR6: 0 | AS6: 0 | AT6: 0 | AU6: 0 | AV6: 0 | AW6: 0 | AX6: 0 | AY6: 0 | AZ6: 0 | BA6: 0 | BB6: 0 | BC6: 0 | BD6: 0 | BE6: 0 | BF6: 0 | BG6: 0 | BH6: 0 | BI6: 0 | BJ6: 0 | BK6: 0 | BL6: 0 | BM6: 0 | BN6: 0 | BO6: 0 | BP6: 0 | BQ6: 0 | BR6: 1 | BS6: 1 | BT6: 0 | BU6: 0 | BV6: 0 | BW6: 0 | BX6: 0 | BY6: 1 | BZ6: 0
A7: 3 | B7: b | C7: 1 | D7: 0 | E7: 0 | F7: 0 | G7: 0 | H7: 0 | I7: 0 | J7: 0 | K7: 0 | L7: 0 | M7: 0 | N7: 0 | O7: 0 | P7: 0 | Q7: 0 | R7: 0 | S7: 0 | T7: 1 | U7: 0 | V7: 0 | W7: 0 | X7: 0 | Y7: 0 | Z7: 1 | AA7: 0 | AB7: 0 | AC7: 0 | AD7: 0 | AE7: 0 | AF7: 0 | AG7: 0 | AH7: 0 | AI7: 0 | AJ7: 0 | AK7: 0 | AL7: 0 | AM7: 0 | AN7: 0 | AO7: 0 | AP7: 0 | AQ7: 0 | AR7: 0 | AS7: 0 | AT7: 0 | AU7: 0 | AV7: 0 | AW7: 0 | AX7: 0 | AY7: 0 | AZ7: 0 | BA7: 0 | BB7: 0 | BC7: 0 | BD7: 0 | BE7: 0 | BF7: 0 | BG7: 0 | BH7: 0 | BI7: 0 | BJ7: 0 | BK7: 0 | BL7: 0 | BM7: 0 | BN7: 0 | BO7: 0 | BP7: 0 | BQ7: 0 | BR7: 0 | BS7: 0 | BT7: 0 | BU7: 0 | BV7: 0 | BW7: 0 | BX7: 0 | BY7: 1 | BZ7: 0
A8: 4 | B8: a | C8: 1 | D8: 0 | E8: 0 | F8: 1 | G8: 0 | H8: 1 | I8: 0 | J8: 0 | K8: 0 | L8: 0 | M8: 0 | N8: 0 | O8: 0 | P8: 0 | Q8: 0 | R8: 0 | S8: 0 | T8: 1 | U8: 0 | V8: 0 | W8: 0 | X8: 1 | Y8: 0 | Z8: 0 | AA8: 0 | AB8: 0 | AC8: 0 | AD8: 0 | AE8: 0 | AF8: 0 | AG8: 0 | AH8: 0 | AI8: 0 | AJ8: 0 | AK8: 0 | AL8: 1 | AM8: 0 | AN8: 0 | AO8: 0 | AP8: 0 | AQ8: 0 | AR8: 0 | AS8: 0 | AT8: 0 | AU8: 0 | AV8: 0 | AW8: 0 | AX8: 0 | AY8: 0 | AZ8: 0 | BA8: 0 | BB8: 0 | BC8: 0 | BD8: 0 | BE8: 0 | BF8: 0 | BG8: 0 | BH8: 0 | BI8: 0 | BJ8: 0 | BK8: 0 | BL8: 0 | BM8: 0 | BN8: 0 | BO8: 0 | BP8: 0 | BQ8: 1 | BR8: 1 | BS8: 1 | BT8: 0 | BU8: 0 | BV8: 0 | BW8: 0 | BX8: 0 | BY8: 0 | BZ8: 0
A9: 4 | B9: b | C9: 0 | D9: 0 | E9: 0 | F9: 0 | G9: 0 | H9: 0 | I9: 0 | J9: 0 | K9: 0 | L9: 0 | M9: 0 | N9: 0 | O9: 0 | P9: 0 | Q9: 0 | R9: 0 | S9: 0 | T9: 0 | U9: 0 | V9: 0 | W9: 0 | X9: 0 | Y9: 0 | Z9: 0 | AA9: 0 | AB9: 0 | AC9: 0 | AD9: 0 | AE9: 0 | AF9: 0 | AG9: 0 | AH9: 0 | AI9: 0 | AJ9: 0 | AK9: 0 | AL9: 0 | AM9: 0 | AN9: 0 | AO9: 0 | AP9: 0 | AQ9: 0 | AR9: 0 | AS9: 0 | AT9: 0 | AU9: 0 | AV9: 0 | AW9: 0 | AX9: 0 | AY9: 0 | AZ9: 0 | BA9: 0 | BB9: 0 | BC9: 0 | BD9: 0 | BE9: 0 | BF9: 0 | BG9: 0 | BH9: 0 | BI9: 0 | BJ9: 0 | BK9: 0 | BL9: 0 | BM9: 0 | BN9: 0 | BO9: 0 | BP9: 0 | BQ9: 0 | BR9: 0 | BS9: 0 | BT9: 0 | BU9: 0 | BV9: 0 | BW9: 0 | BX9: 0 | BY9: 0 | BZ9: 0
A10: 5 | B10: a | C10: 1 | D10: 1 | E10: 0 | F10: 1 | G10: 0 | H10: 0 | I10: 0 | J10: 0 | K10: 0 | L10: 0 | M10: 0 | N10: 0 | O10: 1 | P10: 0 | Q10: 0 | R10: 1 | S10: 0 | T10: 0 | U10: 0 | V10: 0 | W10: 0 | X10: 0 | Y10: 0 | Z10: 1 | AA10: 0 | AB10: 0 | AC10: 0 | AD10: 0 | AE10: 0 | AF10: 0 | AG10: 0 | AH10: 0 | AI10: 0 | AJ10: 0 | AK10: 1 | AL10: 0 | AM10: 0 | AN10: 0 | AO10: 0 | AP10: 0 | AQ10: 1 | AR10: 0 | AS10: 0 | AT10: 0 | AU10: 0 | AV10: 0 | AW10: 0 | AX10: 0 | AY10: 0 | AZ10: 0 | BA10: 0 | BB10: 0 | BC10: 0 | BD10: 1 | BE10: 0 | BF10: 0 | BG10: 0 | BH10: 1 | BI10: 0 | BJ10: 0 | BK10: 0 | BL10: 0 | BM10: 0 | BN10: 0 | BO10: 1 | BP10: 0 | BQ10: 1 | BR10: 0 | BS10: 0 | BT10: 0 | BU10: 1 | BV10: 0 | BW10: 0 | BX10: 0 | BY10: 0 | BZ10: 0
A11: 5 | B11: b | C11: 1 | D11: 0 | E11: 0 | F11: 0 | G11: 0 | H11: 0 | I11: 0 | J11: 0 | K11: 0 | L11: 0 | M11: 0 | N11: 0 | O11: 0 | P11: 0 | Q11: 0 | R11: 0 | S11: 0 | T11: 0 | U11: 0 | V11: 0 | W11: 0 | X11: 0 | Y11: 0 | Z11: 0 | AA11: 0 | AB11: 0 | AC11: 0 | AD11: 0 | AE11: 0 | AF11: 0 | AG11: 0 | AH11: 0 | AI11: 0 | AJ11: 0 | AK11: 0 | AL11: 0 | AM11: 0 | AN11: 0 | AO11: 0 | AP11: 0 | AQ11: 0 | AR11: 0 | AS11: 0 | AT11: 0 | AU11: 0 | AV11: 0 | AW11: 0 | AX11: 0 | AY11: 0 | AZ11: 0 | BA11: 0 | BB11: 0 | BC11: 0 | BD11: 0 | BE11: 0 | BF11: 0 | BG11: 0 | BH11: 0 | BI11: 0 | BJ11: 0 | BK11: 0 | BL11: 0 | BM11: 1 | BN11: 0 | BO11: 1 | BP11: 0 | BQ11: 0 | BR11: 0 | BS11: 0 | BT11: 0 | BU11: 1 | BV11: 0 | BW11: 0 | BX11: 0 | BY11: 1 | BZ11: 0
A12: 6 | B12: a | C12: 1 | D12: 1 | E12: 0 | F12: 1 | G12: 0 | H12: 1 | I12: 0 | J12: 0 | K12: 0 | L12: 1 | M12: 0 | N12: 0 | O12: 0 | P12: 0 | Q12: 0 | R12: 0 | S12: 0 | T12: 0 | U12: 0 | V12: 0 | W12: 1 | X12: 0 | Y12: 0 | Z12: 0 | AA12: 0 | AB12: 0 | AC12: 0 | AD12: 0 | AE12: 1 | AF12: 0 | AG12: 0 | AH12: 0 | AI12: 0 | AJ12: 0 | AK12: 0 | AL12: 0 | AM12: 0 | AN12: 0 | AO12: 0 | AP12: 0 | AQ12: 0 | AR12: 0 | AS12: 0 | AT12: 0 | AU12: 0 | AV12: 0 | AW12: 0 | AX12: 0 | AY12: 0 | AZ12: 0 | BA12: 0 | BB12: 0 | BC12: 0 | BD12: 0 | BE12: 0 | BF12: 0 | BG12: 0 | BH12: 0 | BI12: 0 | BJ12: 0 | BK12: 0 | BL12: 0 | BM12: 0 | BN12: 0 | BO12: 0 | BP12: 0 | BQ12: 0 | BR12: 0 | BS12: 0 | BT12: 0 | BU12: 0 | BV12: 0 | BW12: 0 | BX12: 0 | BY12: 0 | BZ12: 0
A13: 6 | B13: b | C13: 0 | D13: 0 | E13: 0 | F13: 0 | G13: 0 | H13: 0 | I13: 0 | J13: 0 | K13: 0 | L13: 0 | M13: 0 | N13: 0 | O13: 0 | P13: 0 | Q13: 0 | R13: 0 | S13: 0 | T13: 0 | U13: 0 | V13: 0 | W13: 0 | X13: 0 | Y13: 0 | Z13: 0 | AA13: 0 | AB13: 0 | AC13: 0 | AD13: 0 | AE13: 0 | AF13: 0 | AG13: 0 | AH13: 0 | AI13: 0 | AJ13: 0 | AK13: 0 | AL13: 0 | AM13: 0 | AN13: 0 | AO13: 0 | AP13: 0 | AQ13: 0 | AR13: 0 | AS13: 0 | AT13: 0 | AU13: 0 | AV13: 0 | AW13: 0 | AX13: 0 | AY13: 0 | AZ13: 0 | BA13: 0 | BB13: 0 | BC13: 0 | BD13: 0 | BE13: 0 | BF13: 0 | BG13: 0 | BH13: 0 | BI13: 0 | BJ13: 0 | BK13: 0 | BL13: 0 | BM13: 0 | BN13: 0 | BO13: 0 | BP13: 0 | BQ13: 0 | BR13: 0 | BS13: 0 | BT13: 0 | BU13: 0 | BV13: 0 | BW13: 0 | BX13: 0 | BY13: 0 | BZ13: 0
... A797: 398 | B797: b | C797: 0 | D797: 0 | E797: 0 | F797: 1 | G797: 0 | H797: 1 | I797: 0 | J797: 0 | K797: 0 | L797: 0 | M797: 0 | N797: 0 | O797: 1 | P797: 0 | Q797: 0 | R797: 0 | S797: 0 | T797: 0 | U797: 0 | V797: 0 | W797: 0 | X797: 0 | Y797: 0 | Z797: 1 | AA797: 0 | AB797: 0 | AC797: 0 | AD797: 0 | AE797: 0 | AF797: 0 | AG797: 0 | AH797: 0 | AI797: 0 | AJ797: 0 | AK797: 0 | AL797: 0 | AM797: 0 | AN797: 0 | AO797: 0 | AP797: 0 | AQ797: 0 | AR797: 0 | AS797: 0 | AT797: 0 | AU797: 0 | AV797: 0 | AW797: 0 | AX797: 0 | AY797: 0 | AZ797: 0 | BA797: 0 | BB797: 0 | BC797: 0 | BD797: 0 | BE797: 0 | BF797: 0 | BG797: 0 | BH797: 0 | BI797: 0 | BJ797: 0 | BK797: 0 | BL797: 0 | BM797: 0 | BN797: 0 | BO797: 0 | BP797: 0 | BQ797: 0 | BR797: 0 | BS797: 0 | BT797: 0 | BU797: 0 | BV797: 0 | BW797: 0 | BX797: 0 | BY797: 0 | BZ797: 0
C799: =SUM(C2:C797) -> 505 | D799: =SUM(D2:D797) -> 85 | E799: =SUM(E2:E797) -> 73 | F799: =SUM(F2:F797) -> 110 | G799: =SUM(G2:G797) -> 60 | H799: =SUM(H2:H797) -> 297 | I799: =SUM(I2:I797) -> 146 | J799: =SUM(J2:J797) -> 181 | ... BZ799: =SUM(BZ2:BZ797) -> 5

Sheet Level 2 SUM 
A1: Participant Number | B1: Track id | C1: Positive Evaluations | D1: Negative Evaluations | E1: Familiarity | F1: Musical Expressive | G1: Lyrics | H1: Sound/Musical Features | I1: Track Identifier | J1: Other forms of media | K1: Memory | L1: Person | M1: Activity | N1: Imagination | O1: Change | P1: Match
A2: 1 | B2: a | C2: =SUM('ALL_Level 3 '!C2:D2) -> 1 | D2: 0 | E2: =SUM('ALL_Level 3 '!F2:G2) -> 0 | F2: =SUM('ALL_Level 3 '!H2) -> 0 | G2: =SUM('ALL_Level 3 '!I2:J2) -> 0 | H2: =SUM('ALL_Level 3 '!K2:X2) -> 0 | I2: =SUM('ALL_Level 3 '!Y2:AC2) -> 2 | J2: =SUM('ALL_Level 3 '!AD2:AI2) -> 0 | K2: =SUM('ALL_Level 3 '!AJ2:AU2) -> 1 | L2: =SUM('ALL_Level 3 '!AV2:BB2) -> 0 | M2: =SUM('ALL_Level 3 '!BC2:BK2) -> 0 | N2: =SUM('ALL_Level 3 '!BL2:BO2) -> 0 | O2: =SUM('ALL_Level 3 '!BP2:BW2) -> 0 | P2: =SUM('ALL_Level 3 '!BX2) -> 0
A3: 1 | B3: b | C3: =SUM('ALL_Level 3 '!C3:D3) -> 0 | D3: 0 | E3: =SUM('ALL_Level 3 '!F3:G3) -> 1 | F3: =SUM('ALL_Level 3 '!H3) -> 0 | G3: =SUM('ALL_Level 3 '!I3:J3) -> 0 | H3: =SUM('ALL_Level 3 '!K3:X3) -> 0 | I3: =SUM('ALL_Level 3 '!Y3:AC3) -> 0 | J3: =SUM('ALL_Level 3 '!AD3:AI3) -> 0 | K3: =SUM('ALL_Level 3 '!AJ3:AU3) -> 0 | L3: =SUM('ALL_Level 3 '!AV3:BB3) -> 0 | M3: =SUM('ALL_Level 3 '!BC3:BK3) -> 0 | N3: =SUM('ALL_Level 3 '!BL3:BO3) -> 0 | O3: =SUM('ALL_Level 3 '!BP3:BW3) -> 0 | P3: =SUM('ALL_Level 3 '!BX3) -> 0
A4: 2 | B4: a | C4: =SUM('ALL_Level 3 '!C4:D4) -> 1 | D4: 0 | E4: =SUM('ALL_Level 3 '!F4:G4) -> 0 | F4: =SUM('ALL_Level 3 '!H4) -> 0 | G4: =SUM('ALL_Level 3 '!I4:J4) -> 1 | H4: =SUM('ALL_Level 3 '!K4:X4) -> 3 | I4: =SUM('ALL_Level 3 '!Y4:AC4) -> 2 | J4: =SUM('ALL_Level 3 '!AD4:AI4) -> 0 | K4: =SUM('ALL_Level 3 '!AJ4:AU4) -> 2 | L4: =SUM('ALL_Level 3 '!AV4:BB4) -> 0 | M4: =SUM('ALL_Level 3 '!BC4:BK4) -> 0 | N4: =SUM('ALL_Level 3 '!BL4:BO4) -> 0 | O4: =SUM('ALL_Level 3 '!BP4:BW4) -> 0 | P4: =SUM('ALL_Level 3 '!BX4) -> 0
A5: 2 | B5: b | C5: =SUM('ALL_Level 3 '!C5:D5) -> 1 | D5: 0 | E5: =SUM('ALL_Level 3 '!F5:G5) -> 0 | F5: =SUM('ALL_Level 3 '!H5) -> 0 | G5: =SUM('ALL_Level 3 '!I5:J5) -> 1 | H5: =SUM('ALL_Level 3 '!K5:X5) -> 2 | I5: =SUM('ALL_Level 3 '!Y5:AC5) -> 3 | J5: =SUM('ALL_Level 3 '!AD5:AI5) -> 0 | K5: =SUM('ALL_Level 3 '!AJ5:AU5) -> 1 | L5: =SUM('ALL_Level 3 '!AV5:BB5) -> 0 | M5: =SUM('ALL_Level 3 '!BC5:BK5) -> 0 | N5: =SUM('ALL_Level 3 '!BL5:BO5) -> 0 | O5: =SUM('ALL_Level 3 '!BP5:BW5) -> 0 | P5: =SUM('ALL_Level 3 '!BX5) -> 0
A6: 3 | B6: a | C6: =SUM('ALL_Level 3 '!C6:D6) -> 0 | D6: 0 | E6: =SUM('ALL_Level 3 '!F6:G6) -> 0 | F6: =SUM('ALL_Level 3 '!H6) -> 1 | G6: =SUM('ALL_Level 3 '!I6:J6) -> 2 | H6: =SUM('ALL_Level 3 '!K6:X6) -> 1 | I6: =SUM('ALL_Level 3 '!Y6:AC6) -> 0 | J6: =SUM('ALL_Level 3 '!AD6:AI6) -> 0 | K6: =SUM('ALL_Level 3 '!AJ6:AU6) -> 0 | L6: =SUM('ALL_Level 3 '!AV6:BB6) -> 0 | M6: =SUM('ALL_Level 3 '!BC6:BK6) -> 0 | N6: =SUM('ALL_Level 3 '!BL6:BO6) -> 0 | O6: =SUM('ALL_Level 3 '!BP6:BW6) -> 2 | P6: =SUM('ALL_Level 3 '!BX6) -> 0
A7: 3 | B7: b | C7: =SUM('ALL_Level 3 '!C7:D7) -> 1 | D7: 0 | E7: =SUM('ALL_Level 3 '!F7:G7) -> 0 | F7: =SUM('ALL_Level 3 '!H7) -> 0 | G7: =SUM('ALL_Level 3 '!I7:J7) -> 0 | H7: =SUM('ALL_Level 3 '!K7:X7) -> 1 | I7: =SUM('ALL_Level 3 '!Y7:AC7) -> 1 | J7: =SUM('ALL_Level 3 '!AD7:AI7) -> 0 | K7: =SUM('ALL_Level 3 '!AJ7:AU7) -> 0 | L7: =SUM('ALL_Level 3 '!AV7:BB7) -> 0 | M7: =SUM('ALL_Level 3 '!BC7:BK7) -> 0 | N7: =SUM('ALL_Level 3 '!BL7:BO7) -> 0 | O7: =SUM('ALL_Level 3 '!BP7:BW7) -> 0 | P7: =SUM('ALL_Level 3 '!BX7) -> 0
A8: 4 | B8: a | C8: =SUM('ALL_Level 3 '!C8:D8) -> 1 | D8: 0 | E8: =SUM('ALL_Level 3 '!F8:G8) -> 1 | F8: =SUM('ALL_Level 3 '!H8) -> 1 | G8: =SUM('ALL_Level 3 '!I8:J8) -> 0 | H8: =SUM('ALL_Level 3 '!K8:X8) -> 2 | I8: =SUM('ALL_Level 3 '!Y8:AC8) -> 0 | J8: =SUM('ALL_Level 3 '!AD8:AI8) -> 0 | K8: =SUM('ALL_Level 3 '!AJ8:AU8) -> 1 | L8: =SUM('ALL_Level 3 '!AV8:BB8) -> 0 | M8: =SUM('ALL_Level 3 '!BC8:BK8) -> 0 | N8: =SUM('ALL_Level 3 '!BL8:BO8) -> 0 | O8: =SUM('ALL_Level 3 '!BP8:BW8) -> 3 | P8: =SUM('ALL_Level 3 '!BX8) -> 0
A9: 4 | B9: b | C9: =SUM('ALL_Level 3 '!C9:D9) -> 0 | D9: 0 | E9: =SUM('ALL_Level 3 '!F9:G9) -> 0 | F9: =SUM('ALL_Level 3 '!H9) -> 0 | G9: =SUM('ALL_Level 3 '!I9:J9) -> 0 | H9: =SUM('ALL_Level 3 '!K9:X9) -> 0 | I9: =SUM('ALL_Level 3 '!Y9:AC9) -> 0 | J9: =SUM('ALL_Level 3 '!AD9:AI9) -> 0 | K9: =SUM('ALL_Level 3 '!AJ9:AU9) -> 0 | L9: =SUM('ALL_Level 3 '!AV9:BB9) -> 0 | M9: =SUM('ALL_Level 3 '!BC9:BK9) -> 0 | N9: =SUM('ALL_Level 3 '!BL9:BO9) -> 0 | O9: =SUM('ALL_Level 3 '!BP9:BW9) -> 0 | P9: =SUM('ALL_Level 3 '!BX9) -> 0
A10: 5 | B10: a | C10: =SUM('ALL_Level 3 '!C10:D10) -> 2 | D10: 0 | E10: =SUM('ALL_Level 3 '!F10:G10) -> 1 | F10: =SUM('ALL_Level 3 '!H10) -> 0 | G10: =SUM('ALL_Level 3 '!I10:J10) -> 0 | H10: =SUM('ALL_Level 3 '!K10:X10) -> 2 | I10: =SUM('ALL_Level 3 '!Y10:AC10) -> 1 | J10: =SUM('ALL_Level 3 '!AD10:AI10) -> 0 | K10: =SUM('ALL_Level 3 '!AJ10:AU10) -> 2 | L10: =SUM('ALL_Level 3 '!AV10:BB10) -> 0 | M10: =SUM('ALL_Level 3 '!BC10:BK10) -> 2 | N10: =SUM('ALL_Level 3 '!BL10:BO10) -> 1 | O10: =SUM('ALL_Level 3 '!BP10:BW10) -> 2 | P10: =SUM('ALL_Level 3 '!BX10) -> 0
A11: 5 | B11: b | C11: =SUM('ALL_Level 3 '!C11:D11) -> 1 | D11: 0 | E11: =SUM('ALL_Level 3 '!F11:G11) -> 0 | F11: =SUM('ALL_Level 3 '!H11) -> 0 | G11: =SUM('ALL_Level 3 '!I11:J11) -> 0 | H11: =SUM('ALL_Level 3 '!K11:X11) -> 0 | I11: =SUM('ALL_Level 3 '!Y11:AC11) -> 0 | J11: =SUM('ALL_Level 3 '!AD11:AI11) -> 0 | K11: =SUM('ALL_Level 3 '!AJ11:AU11) -> 0 | L11: =SUM('ALL_Level 3 '!AV11:BB11) -> 0 | M11: =SUM('ALL_Level 3 '!BC11:BK11) -> 0 | N11: =SUM('ALL_Level 3 '!BL11:BO11) -> 2 | O11: =SUM('ALL_Level 3 '!BP11:BW11) -> 1 | P11: =SUM('ALL_Level 3 '!BX11) -> 0
A12: 6 | B12: a | C12: =SUM('ALL_Level 3 '!C12:D12) -> 2 | D12: 0 | E12: =SUM('ALL_Level 3 '!F12:G12) -> 1 | F12: =SUM('ALL_Level 3 '!H12) -> 1 | G12: =SUM('ALL_Level 3 '!I12:J12) -> 0 | H12: =SUM('ALL_Level 3 '!K12:X12) -> 2 | I12: =SUM('ALL_Level 3 '!Y12:AC12) -> 0 | J12: =SUM('ALL_Level 3 '!AD12:AI12) -> 1 | K12: =SUM('ALL_Level 3 '!AJ12:AU12) -> 0 | L12: =SUM('ALL_Level 3 '!AV12:BB12) -> 0 | M12: =SUM('ALL_Level 3 '!BC12:BK12) -> 0 | N12: =SUM('ALL_Level 3 '!BL12:BO12) -> 0 | O12: =SUM('ALL_Level 3 '!BP12:BW12) -> 0 | P12: =SUM('ALL_Level 3 '!BX12) -> 0
A13: 6 | B13: b | C13: =SUM('ALL_Level 3 '!C13:D13) -> 0 | D13: 0 | E13: =SUM('ALL_Level 3 '!F13:G13) -> 0 | F13: =SUM('ALL_Level 3 '!H13) -> 0 | G13: =SUM('ALL_Level 3 '!I13:J13) -> 0 | H13: =SUM('ALL_Level 3 '!K13:X13) -> 0 | I13: =SUM('ALL_Level 3 '!Y13:AC13) -> 0 | J13: =SUM('ALL_Level 3 '!AD13:AI13) -> 0 | K13: =SUM('ALL_Level 3 '!AJ13:AU13) -> 0 | L13: =SUM('ALL_Level 3 '!AV13:BB13) -> 0 | M13: =SUM('ALL_Level 3 '!BC13:BK13) -> 0 | N13: =SUM('ALL_Level 3 '!BL13:BO13) -> 0 | O13: =SUM('ALL_Level 3 '!BP13:BW13) -> 0 | P13: =SUM('ALL_Level 3 '!BX13) -> 0
... A797: 398 | B797: b | C797: =SUM('ALL_Level 3 '!C797:D797) -> 0 | D797: 0 | E797: =SUM('ALL_Level 3 '!F797:G797) -> 1 | F797: =SUM('ALL_Level 3 '!H797) -> 1 | G797: =SUM('ALL_Level 3 '!I797:J797) -> 0 | H797: =SUM('ALL_Level 3 '!K797:X797) -> 1 | I797: =SUM('ALL_Level 3 '!Y797:AC797) -> 1 | J797: =SUM('ALL_Level 3 '!AD797:AI797) -> 0 | K797: =SUM('ALL_Level 3 '!AJ797:AU797) -> 0 | L797: =SUM('ALL_Level 3 '!AV797:BB797) -> 0 | M797: =SUM('ALL_Level 3 '!BC797:BK797) -> 0 | N797: =SUM('ALL_Level 3 '!BL797:BO797) -> 0 | O797: =SUM('ALL_Level 3 '!BP797:BW797) -> 0 | P797: =SUM('ALL_Level 3 '!BX797) -> 0

Sheet Level 2 Codes
A1: Participant Number | B1: Track id | C1: Positive Evaluations | D1: Negative Evaluations | E1: Familiarity | F1: Musical Expressive | G1: Lyrics | H1: Sound/Musical Features | I1: Track Identifier | J1: Other forms of media | K1: Memory | L1: Person | M1: Activity | N1: Imagination | O1: Change | P1: Match
A2: 1 | B2: a | C2: =IF('Level 2 SUM '!C2= 0, 0, 1) -> 1 | D2: =IF('Level 2 SUM '!D2= 0, 0, 1) -> 0 | E2: =IF('Level 2 SUM '!E2= 0, 0, 1) -> 0 | F2: =IF('Level 2 SUM '!F2= 0, 0, 1) -> 0 | G2: =IF('Level 2 SUM '!G2= 0, 0, 1) -> 0 | H2: =IF('Level 2 SUM '!H2= 0, 0, 1) -> 0 | I2: =IF('Level 2 SUM '!I2= 0, 0, 1) -> 1 | J2: =IF('Level 2 SUM '!J2= 0, 0, 1) -> 0 | ... P2: =IF('Level 2 SUM '!P2= 0, 0, 1) -> 0
A3: 1 | B3: b | C3: =IF('Level 2 SUM '!C3= 0, 0, 1) -> 0 | D3: =IF('Level 2 SUM '!D3= 0, 0, 1) -> 0 | E3: =IF('Level 2 SUM '!E3= 0, 0, 1) -> 1 | F3: =IF('Level 2 SUM '!F3= 0, 0, 1) -> 0 | G3: =IF('Level 2 SUM '!G3= 0, 0, 1) -> 0 | H3: =IF('Level 2 SUM '!H3= 0, 0, 1) -> 0 | I3: =IF('Level 2 SUM '!I3= 0, 0, 1) -> 0 | J3: =IF('Level 2 SUM '!J3= 0, 0, 1) -> 0 | ... P3: =IF('Level 2 SUM '!P3= 0, 0, 1) -> 0
A4: 2 | B4: a | C4: =IF('Level 2 SUM '!C4= 0, 0, 1) -> 1 | D4: =IF('Level 2 SUM '!D4= 0, 0, 1) -> 0 | E4: =IF('Level 2 SUM '!E4= 0, 0, 1) -> 0 | F4: =IF('Level 2 SUM '!F4= 0, 0, 1) -> 0 | G4: =IF('Level 2 SUM '!G4= 0, 0, 1) -> 1 | H4: =IF('Level 2 SUM '!H4= 0, 0, 1) -> 1 | I4: =IF('Level 2 SUM '!I4= 0, 0, 1) -> 1 | J4: =IF('Level 2 SUM '!J4= 0, 0, 1) -> 0 | ... P4: =IF('Level 2 SUM '!P4= 0, 0, 1) -> 0
A5: 2 | B5: b | C5: =IF('Level 2 SUM '!C5= 0, 0, 1) -> 1 | D5: =IF('Level 2 SUM '!D5= 0, 0, 1) -> 0 | E5: =IF('Level 2 SUM '!E5= 0, 0, 1) -> 0 | F5: =IF('Level 2 SUM '!F5= 0, 0, 1) -> 0 | G5: =IF('Level 2 SUM '!G5= 0, 0, 1) -> 1 | H5: =IF('Level 2 SUM '!H5= 0, 0, 1) -> 1 | I5: =IF('Level 2 SUM '!I5= 0, 0, 1) -> 1 | J5: =IF('Level 2 SUM '!J5= 0, 0, 1) -> 0 | ... P5: =IF('Level 2 SUM '!P5= 0, 0, 1) -> 0
A6: 3 | B6: a | C6: =IF('Level 2 SUM '!C6= 0, 0, 1) -> 0 | D6: =IF('Level 2 SUM '!D6= 0, 0, 1) -> 0 | E6: =IF('Level 2 SUM '!E6= 0, 0, 1) -> 0 | F6: =IF('Level 2 SUM '!F6= 0, 0, 1) -> 1 | G6: =IF('Level 2 SUM '!G6= 0, 0, 1) -> 1 | H6: =IF('Level 2 SUM '!H6= 0, 0, 1) -> 1 | I6: =IF('Level 2 SUM '!I6= 0, 0, 1) -> 0 | J6: =IF('Level 2 SUM '!J6= 0, 0, 1) -> 0 | ... P6: =IF('Level 2 SUM '!P6= 0, 0, 1) -> 0
A7: 3 | B7: b | C7: =IF('Level 2 SUM '!C7= 0, 0, 1) -> 1 | D7: =IF('Level 2 SUM '!D7= 0, 0, 1) -> 0 | E7: =IF('Level 2 SUM '!E7= 0, 0, 1) -> 0 | F7: =IF('Level 2 SUM '!F7= 0, 0, 1) -> 0 | G7: =IF('Level 2 SUM '!G7= 0, 0, 1) -> 0 | H7: =IF('Level 2 SUM '!H7= 0, 0, 1) -> 1 | I7: =IF('Level 2 SUM '!I7= 0, 0, 1) -> 1 | J7: =IF('Level 2 SUM '!J7= 0, 0, 1) -> 0 | ... P7: =IF('Level 2 SUM '!P7= 0, 0, 1) -> 0
A8: 4 | B8: a | C8: =IF('Level 2 SUM '!C8= 0, 0, 1) -> 1 | D8: =IF('Level 2 SUM '!D8= 0, 0, 1) -> 0 | E8: =IF('Level 2 SUM '!E8= 0, 0, 1) -> 1 | F8: =IF('Level 2 SUM '!F8= 0, 0, 1) -> 1 | G8: =IF('Level 2 SUM '!G8= 0, 0, 1) -> 0 | H8: =IF('Level 2 SUM '!H8= 0, 0, 1) -> 1 | I8: =IF('Level 2 SUM '!I8= 0, 0, 1) -> 0 | J8: =IF('Level 2 SUM '!J8= 0, 0, 1) -> 0 | ... P8: =IF('Level 2 SUM '!P8= 0, 0, 1) -> 0
A9: 4 | B9: b | C9: =IF('Level 2 SUM '!C9= 0, 0, 1) -> 0 | D9: =IF('Level 2 SUM '!D9= 0, 0, 1) -> 0 | E9: =IF('Level 2 SUM '!E9= 0, 0, 1) -> 0 | F9: =IF('Level 2 SUM '!F9= 0, 0, 1) -> 0 | G9: =IF('Level 2 SUM '!G9= 0, 0, 1) -> 0 | H9: =IF('Level 2 SUM '!H9= 0, 0, 1) -> 0 | I9: =IF('Level 2 SUM '!I9= 0, 0, 1) -> 0 | J9: =IF('Level 2 SUM '!J9= 0, 0, 1) -> 0 | ... P9: =IF('Level 2 SUM '!P9= 0, 0, 1) -> 0
A10: 5 | B10: a | C10: =IF('Level 2 SUM '!C10= 0, 0, 1) -> 1 | D10: =IF('Level 2 SUM '!D10= 0, 0, 1) -> 0 | E10: =IF('Level 2 SUM '!E10= 0, 0, 1) -> 1 | F10: =IF('Level 2 SUM '!F10= 0, 0, 1) -> 0 | G10: =IF('Level 2 SUM '!G10= 0, 0, 1) -> 0 | H10: =IF('Level 2 SUM '!H10= 0, 0, 1) -> 1 | I10: =IF('Level 2 SUM '!I10= 0, 0, 1) -> 1 | J10: =IF('Level 2 SUM '!J10= 0, 0, 1) -> 0 | ... P10: =IF('Level 2 SUM '!P10= 0, 0, 1) -> 0
A11: 5 | B11: b | C11: =IF('Level 2 SUM '!C11= 0, 0, 1) -> 1 | D11: =IF('Level 2 SUM '!D11= 0, 0, 1) -> 0 | E11: =IF('Level 2 SUM '!E11= 0, 0, 1) -> 0 | F11: =IF('Level 2 SUM '!F11= 0, 0, 1) -> 0 | G11: =IF('Level 2 SUM '!G11= 0, 0, 1) -> 0 | H11: =IF('Level 2 SUM '!H11= 0, 0, 1) -> 0 | I11: =IF('Level 2 SUM '!I11= 0, 0, 1) -> 0 | J11: =IF('Level 2 SUM '!J11= 0, 0, 1) -> 0 | ... P11: =IF('Level 2 SUM '!P11= 0, 0, 1) -> 0
A12: 6 | B12: a | C12: =IF('Level 2 SUM '!C12= 0, 0, 1) -> 1 | D12: =IF('Level 2 SUM '!D12= 0, 0, 1) -> 0 | E12: =IF('Level 2 SUM '!E12= 0, 0, 1) -> 1 | F12: =IF('Level 2 SUM '!F12= 0, 0, 1) -> 1 | G12: =IF('Level 2 SUM '!G12= 0, 0, 1) -> 0 | H12: =IF('Level 2 SUM '!H12= 0, 0, 1) -> 1 | I12: =IF('Level 2 SUM '!I12= 0, 0, 1) -> 0 | J12: =IF('Level 2 SUM '!J12= 0, 0, 1) -> 1 | ... P12: =IF('Level 2 SUM '!P12= 0, 0, 1) -> 0
A13: 6 | B13: b | C13: =IF('Level 2 SUM '!C13= 0, 0, 1) -> 0 | D13: =IF('Level 2 SUM '!D13= 0, 0, 1) -> 0 | E13: =IF('Level 2 SUM '!E13= 0, 0, 1) -> 0 | F13: =IF('Level 2 SUM '!F13= 0, 0, 1) -> 0 | G13: =IF('Level 2 SUM '!G13= 0, 0, 1) -> 0 | H13: =IF('Level 2 SUM '!H13= 0, 0, 1) -> 0 | I13: =IF('Level 2 SUM '!I13= 0, 0, 1) -> 0 | J13: =IF('Level 2 SUM '!J13= 0, 0, 1) -> 0 | ... P13: =IF('Level 2 SUM '!P13= 0, 0, 1) -> 0
... A797: 398 | B797: b | C797: =IF('Level 2 SUM '!C797= 0, 0, 1) -> 0 | D797: =IF('Level 2 SUM '!D797= 0, 0, 1) -> 0 | E797: =IF('Level 2 SUM '!E797= 0, 0, 1) -> 1 | F797: =IF('Level 2 SUM '!F797= 0, 0, 1) -> 1 | G797: =IF('Level 2 SUM '!G797= 0, 0, 1) -> 0 | H797: =IF('Level 2 SUM '!H797= 0, 0, 1) -> 1 | I797: =IF('Level 2 SUM '!I797= 0, 0, 1) -> 1 | J797: =IF('Level 2 SUM '!J797= 0, 0, 1) -> 0 | ... P797: =IF('Level 2 SUM '!P797= 0, 0, 1) -> 0

Sheet Level 1  SUM 
A1: Participant Number | B1: Track id | C1: Evaluations | D1: Characteristics | E1: Associations | F1: Responses Induced
A2: 1 | B2: a | C2: =SUM('Level 2 SUM '!C2:E2) -> 1 | D2: =SUM('Level 2 SUM '!F2:H2) -> 0 | E2: =SUM('Level 2 SUM '!I2:N2) -> 3 | F2: =SUM('Level 2 SUM '!O2:P2) -> 0
A3: 1 | B3: b | C3: =SUM('Level 2 SUM '!C3:E3) -> 1 | D3: =SUM('Level 2 SUM '!F3:H3) -> 0 | E3: =SUM('Level 2 SUM '!I3:N3) -> 0 | F3: =SUM('Level 2 SUM '!O3:P3) -> 0
A4: 2 | B4: a | C4: =SUM('Level 2 SUM '!C4:E4) -> 1 | D4: =SUM('Level 2 SUM '!F4:H4) -> 4 | E4: =SUM('Level 2 SUM '!I4:N4) -> 4 | F4: =SUM('Level 2 SUM '!O4:P4) -> 0
A5: 2 | B5: b | C5: =SUM('Level 2 SUM '!C5:E5) -> 1 | D5: =SUM('Level 2 SUM '!F5:H5) -> 3 | E5: =SUM('Level 2 SUM '!I5:N5) -> 4 | F5: =SUM('Level 2 SUM '!O5:P5) -> 0
A6: 3 | B6: a | C6: =SUM('Level 2 SUM '!C6:E6) -> 0 | D6: =SUM('Level 2 SUM '!F6:H6) -> 4 | E6: =SUM('Level 2 SUM '!I6:N6) -> 0 | F6: =SUM('Level 2 SUM '!O6:P6) -> 2
A7: 3 | B7: b | C7: =SUM('Level 2 SUM '!C7:E7) -> 1 | D7: =SUM('Level 2 SUM '!F7:H7) -> 1 | E7: =SUM('Level 2 SUM '!I7:N7) -> 1 | F7: =SUM('Level 2 SUM '!O7:P7) -> 0
A8: 4 | B8: a | C8: =SUM('Level 2 SUM '!C8:E8) -> 2 | D8: =SUM('Level 2 SUM '!F8:H8) -> 3 | E8: =SUM('Level 2 SUM '!I8:N8) -> 1 | F8: =SUM('Level 2 SUM '!O8:P8) -> 3
A9: 4 | B9: b | C9: =SUM('Level 2 SUM '!C9:E9) -> 0 | D9: =SUM('Level 2 SUM '!F9:H9) -> 0 | E9: =SUM('Level 2 SUM '!I9:N9) -> 0 | F9: =SUM('Level 2 SUM '!O9:P9) -> 0
A10: 5 | B10: a | C10: =SUM('Level 2 SUM '!C10:E10) -> 3 | D10: =SUM('Level 2 SUM '!F10:H10) -> 2 | E10: =SUM('Level 2 SUM '!I10:N10) -> 6 | F10: =SUM('Level 2 SUM '!O10:P10) -> 2
A11: 5 | B11: b | C11: =SUM('Level 2 SUM '!C11:E11) -> 1 | D11: =SUM('Level 2 SUM '!F11:H11) -> 0 | E11: =SUM('Level 2 SUM '!I11:N11) -> 2 | F11: =SUM('Level 2 SUM '!O11:P11) -> 1
A12: 6 | B12: a | C12: =SUM('Level 2 SUM '!C12:E12) -> 3 | D12: =SUM('Level 2 SUM '!F12:H12) -> 3 | E12: =SUM('Level 2 SUM '!I12:N12) -> 1 | F12: =SUM('Level 2 SUM '!O12:P12) -> 0
A13: 6 | B13: b | C13: =SUM('Level 2 SUM '!C13:E13) -> 0 | D13: =SUM('Level 2 SUM '!F13:H13) -> 0 | E13: =SUM('Level 2 SUM '!I13:N13) -> 0 | F13: =SUM('Level 2 SUM '!O13:P13) -> 0
... A797: 398 | B797: b | C797: =SUM('Level 2 SUM '!C797:E797) -> 1 | D797: =SUM('Level 2 SUM '!F797:H797) -> 2 | E797: =SUM('Level 2 SUM '!I797:N797) -> 1 | F797: =SUM('Level 2 SUM '!O797:P797) -> 0

Sheet Level 1 Code
A1: Participant Number | B1: Track id | C1: Evaluations | D1: Characteristics | E1: Associations | F1: Responses Induced
A2: 1 | B2: a | C2: =IF('Level 1 SUM '!C2 = 0, 0, 1) -> 1 | D2: =IF('Level 1 SUM '!D2 = 0, 0, 1) -> 0 | E2: =IF('Level 1 SUM '!E2 = 0, 0, 1) -> 1 | F2: =IF('Level 1 SUM '!F2 = 0, 0, 1) -> 0
A3: 1 | B3: b | C3: =IF('Level 1 SUM '!C3 = 0, 0, 1) -> 1 | D3: =IF('Level 1 SUM '!D3 = 0, 0, 1) -> 0 | E3: =IF('Level 1 SUM '!E3 = 0, 0, 1) -> 0 | F3: =IF('Level 1 SUM '!F3 = 0, 0, 1) -> 0
A4: 2 | B4: a | C4: =IF('Level 1 SUM '!C4 = 0, 0, 1) -> 1 | D4: =IF('Level 1 SUM '!D4 = 0, 0, 1) -> 1 | E4: =IF('Level 1 SUM '!E4 = 0, 0, 1) -> 1 | F4: =IF('Level 1 SUM '!F4 = 0, 0, 1) -> 0
A5: 2 | B5: b | C5: =IF('Level 1 SUM '!C5 = 0, 0, 1) -> 1 | D5: =IF('Level 1 SUM '!D5 = 0, 0, 1) -> 1 | E5: =IF('Level 1 SUM '!E5 = 0, 0, 1) -> 1 | F5: =IF('Level 1 SUM '!F5 = 0, 0, 1) -> 0
A6: 3 | B6: a | C6: =IF('Level 1 SUM '!C6 = 0, 0, 1) -> 0 | D6: =IF('Level 1 SUM '!D6 = 0, 0, 1) -> 1 | E6: =IF('Level 1 SUM '!E6 = 0, 0, 1) -> 0 | F6: =IF('Level 1 SUM '!F6 = 0, 0, 1) -> 1
A7: 3 | B7: b | C7: =IF('Level 1 SUM '!C7 = 0, 0, 1) -> 1 | D7: =IF('Level 1 SUM '!D7 = 0, 0, 1) -> 1 | E7: =IF('Level 1 SUM '!E7 = 0, 0, 1) -> 1 | F7: =IF('Level 1 SUM '!F7 = 0, 0, 1) -> 0
A8: 4 | B8: a | C8: =IF('Level 1 SUM '!C8 = 0, 0, 1) -> 1 | D8: =IF('Level 1 SUM '!D8 = 0, 0, 1) -> 1 | E8: =IF('Level 1 SUM '!E8 = 0, 0, 1) -> 1 | F8: =IF('Level 1 SUM '!F8 = 0, 0, 1) -> 1
A9: 4 | B9: b | C9: =IF('Level 1 SUM '!C9 = 0, 0, 1) -> 0 | D9: =IF('Level 1 SUM '!D9 = 0, 0, 1) -> 0 | E9: =IF('Level 1 SUM '!E9 = 0, 0, 1) -> 0 | F9: =IF('Level 1 SUM '!F9 = 0, 0, 1) -> 0
A10: 5 | B10: a | C10: =IF('Level 1 SUM '!C10 = 0, 0, 1) -> 1 | D10: =IF('Level 1 SUM '!D10 = 0, 0, 1) -> 1 | E10: =IF('Level 1 SUM '!E10 = 0, 0, 1) -> 1 | F10: =IF('Level 1 SUM '!F10 = 0, 0, 1) -> 1
A11: 5 | B11: b | C11: =IF('Level 1 SUM '!C11 = 0, 0, 1) -> 1 | D11: =IF('Level 1 SUM '!D11 = 0, 0, 1) -> 0 | E11: =IF('Level 1 SUM '!E11 = 0, 0, 1) -> 1 | F11: =IF('Level 1 SUM '!F11 = 0, 0, 1) -> 1
A12: 6 | B12: a | C12: =IF('Level 1 SUM '!C12 = 0, 0, 1) -> 1 | D12: =IF('Level 1 SUM '!D12 = 0, 0, 1) -> 1 | E12: =IF('Level 1 SUM '!E12 = 0, 0, 1) -> 1 | F12: =IF('Level 1 SUM '!F12 = 0, 0, 1) -> 0
A13: 6 | B13: b | C13: =IF('Level 1 SUM '!C13 = 0, 0, 1) -> 0 | D13: =IF('Level 1 SUM '!D13 = 0, 0, 1) -> 0 | E13: =IF('Level 1 SUM '!E13 = 0, 0, 1) -> 0 | F13: =IF('Level 1 SUM '!F13 = 0, 0, 1) -> 0
... A797: 398 | B797: b | C797: =IF('Level 1 SUM '!C797 = 0, 0, 1) -> 1 | D797: =IF('Level 1 SUM '!D797 = 0, 0, 1) -> 1 | E797: =IF('Level 1 SUM '!E797 = 0, 0, 1) -> 1 | F797: =IF('Level 1 SUM '!F797 = 0, 0, 1) -> 0
